{
  "show": {
    "id": 201794,
    "slug": "vishnu-puranam-1",
    "title": "Vishnu Puranam",
    "image": "https://images.cdn.kukufm.com/f:webp/https://s3.ap-south-1.amazonaws.com/kukufm/channel_icons/079c93f521434619a89b7d525b9643c7.png",
    "original_image": "https://s3.ap-south-1.amazonaws.com/kukufm/channel_icons/079c93f521434619a89b7d525b9643c7.png",
    "image_sizes": {
      "100": "https://images.cdn.kukufm.com/w:100/f:webp/q:85/https://s3.ap-south-1.amazonaws.com/kukufm/channel_icons/079c93f521434619a89b7d525b9643c7.png",
      "200": "https://images.cdn.kukufm.com/w:200/f:webp/q:85/https://s3.ap-south-1.amazonaws.com/kukufm/channel_icons/079c93f521434619a89b7d525b9643c7.png",
      "300": "https://images.cdn.kukufm.com/w:300/f:webp/q:85/https://s3.ap-south-1.amazonaws.com/kukufm/channel_icons/079c93f521434619a89b7d525b9643c7.png"
    },
    "language": "tamil",
    "published_on": "2023-08-04T05:20:14.558563+00:00",
    "status": "live",
    "n_listens": 122045,
    "is_verified": false,
    "dynamic_link": "https://applinks.kukufm.com/kxgpcus5jHKVbxyA9",
    "uri": "app://kukufm/show/vishnu-puranam-1/",
    "web_uri": "/show/vishnu-puranam-1",
    "share_image_url": "https://images.cdn.kukufm.com/w:300/f:webp/q:85/https://s3.ap-south-1.amazonaws.com/kukufm/channel_icons/079c93f521434619a89b7d525b9643c7.png",
    "cover_type": null,
    "is_premium": true,
    "overall_rating": 4.791,
    "n_reviews": 73,
    "is_fictional": false,
    "duration_s": 20465,
    "n_episodes": 29,
    "n_comments": 0,
    "is_transcript_available": true,
    "n_impressions": 0,
    "recommendation_score": 0,
    "users_completion_p": 0,
    "daily_unlock_count": 0,
    "thumbnail_color": "#33908b67",
    "is_daily_unlock_enabled": false,
    "n_seasons": 1,
    "is_coin_based": false,
    "monetization_type": "subscription",
    "is_coin_premium": false,
    "show_label_info": {},
    "is_coming_soon": null,
    "show_type": "cu_show",
    "is_comments_exposure_enabled": false,
    "is_adult_content": false,
    "sharing_text": "हेलो! मैंने कुकू एफएम पर इस शो को सुना और मेरे ख्‍याल से आपको भी पसंद आएगा",
    "sharing_text_v2": "हेलो! मैंने Kuku FM (Android)  पर यह शो सुना और मुझे यकीन है कि आपको भी यह जरूर पसंद आएगा। \nhttps://links.kukufm.com/7UyWb4",
    "completion_status": 1,
    "description": "Vishnu puranam ah muzhumai ah indha audio book vadivula kelunga. ",
    "description_secondary": "Vishnu puranam ah muzhumai ah indha audio book vadivula kelunga. ",
    "author": {
      "id": 28287293,
      "name": "Booshitha",
      "avatar_cdn": "https://images.cdn.kukufm.com/https://kukufm.s3.amazonaws.com/avatars/5c7aa638f3394365a3f7b449c36e3a39.png",
      "original_avatar": "https://kukufm.s3.amazonaws.com/avatars/5c7aa638f3394365a3f7b449c36e3a39.png",
      "avatar": {
        "32": "https://images.cdn.kukufm.com/w:32/f:jpg/q:90/https://kukufm.s3.amazonaws.com/avatars/5c7aa638f3394365a3f7b449c36e3a39.png",
        "64": "https://images.cdn.kukufm.com/w:64/f:jpg/q:90/https://kukufm.s3.amazonaws.com/avatars/5c7aa638f3394365a3f7b449c36e3a39.png",
        "128": "https://images.cdn.kukufm.com/w:128/f:jpg/q:90/https://kukufm.s3.amazonaws.com/avatars/5c7aa638f3394365a3f7b449c36e3a39.png",
        "256": "https://images.cdn.kukufm.com/w:256/f:jpg/q:90/https://kukufm.s3.amazonaws.com/avatars/5c7aa638f3394365a3f7b449c36e3a39.png"
      },
      "bio": "Play What You Love",
      "incognito_mode": false
    },
    "lang": {
      "id": 8,
      "title": "தமிழ்",
      "title_secondary": "Tamil",
      "image": "https://images.cdn.kukufm.com/https://kukufm.s3.ap-south-1.amazonaws.com/icons/tamil_2.png",
      "slug": "tamil",
      "color": "#282E34",
      "uri": "app://kukufm/home-lang/tamil",
      "web_uri": "/home-lang/tamil",
      "color_info": {
        "bg_color": "#EBCEF5",
        "text_color": "#671584"
      },
      "short_title": "த",
      "svg_icon": "https://d1l07mcd18xic4.cloudfront.net/lang_icons/tamil.svg",
      "icon_sizes": {
        "16": "https://images.cdn.kukufm.com/w:16/q:85/https://kukufm.s3.ap-south-1.amazonaws.com/icons/tamil_2.png",
        "64": "https://images.cdn.kukufm.com/w:64/q:85/https://kukufm.s3.ap-south-1.amazonaws.com/icons/tamil_2.png",
        "256": "https://images.cdn.kukufm.com/w:256/q:85/https://kukufm.s3.ap-south-1.amazonaws.com/icons/tamil_2.png"
      }
    },
    "content_type": {
      "id": 12,
      "title": "फुल बुक्‍स",
      "slug": "audio-book",
      "uri": "app://kukufm/content-types/audio-book",
      "web_uri": "/content-types/audio-book",
      "color_info": {
        "bg_color": "#40C2B3",
        "text_color": "#40C2B3"
      }
    },
    "other_images": {
      "landscape_image": "https://images.cdn.kukufm.com/f:webp/https://s3.ap-south-1.amazonaws.com/kukufm/channel_icons/3edff9a8fc9942d29845f2200ca5eaab_landscape_622.jpg",
      "landscape_image_sizes": {
        "360": "https://images.cdn.kukufm.com/w:360/f:webp/q:85/https://s3.ap-south-1.amazonaws.com/kukufm/channel_icons/3edff9a8fc9942d29845f2200ca5eaab_landscape_622.jpg",
        "480": "https://images.cdn.kukufm.com/w:480/f:webp/q:85/https://s3.ap-south-1.amazonaws.com/kukufm/channel_icons/3edff9a8fc9942d29845f2200ca5eaab_landscape_622.jpg",
        "720": "https://images.cdn.kukufm.com/w:720/f:webp/q:85/https://s3.ap-south-1.amazonaws.com/kukufm/channel_icons/3edff9a8fc9942d29845f2200ca5eaab_landscape_622.jpg"
      },
      "vertical_thumbnail": null,
      "vertical_thumbnail_image_sizes": {
        "360": "https://images.cdn.kukufm.com/w:360/f:webp/q:85/https://s3.ap-south-1.amazonaws.com/kukufm/channel_icons/079c93f521434619a89b7d525b9643c7.png",
        "480": "https://images.cdn.kukufm.com/w:480/f:webp/q:85/https://s3.ap-south-1.amazonaws.com/kukufm/channel_icons/079c93f521434619a89b7d525b9643c7.png",
        "720": "https://images.cdn.kukufm.com/w:720/f:webp/q:85/https://s3.ap-south-1.amazonaws.com/kukufm/channel_icons/079c93f521434619a89b7d525b9643c7.png"
      }
    },
    "thumbnail_data": {},
    "labels": [
      "All Episodes",
      "13+"
    ],
    "is_top_10": false,
    "is_reel": false,
    "ever_been_vip_show": false,
    "resume_episode": {
      "id": 671129,
      "title": "Miga mukkiya moondravathu puranam",
      "slug": "vishnupuranam-intro",
      "status": "live",
      "image": "https://images.cdn.kukufm.com/f:webp/https://s3.ap-south-1.amazonaws.com/kukufm/channel_icons/079c93f521434619a89b7d525b9643c7.png",
      "original_image": "https://s3.ap-south-1.amazonaws.com/kukufm/channel_icons/079c93f521434619a89b7d525b9643c7.png",
      "duration_s": 265,
      "image_sizes": {
        "100": "https://images.cdn.kukufm.com/w:100/f:webp/q:85/https://s3.ap-south-1.amazonaws.com/kukufm/channel_icons/079c93f521434619a89b7d525b9643c7.png",
        "150": "https://images.cdn.kukufm.com/w:150/f:webp/q:85/https://s3.ap-south-1.amazonaws.com/kukufm/channel_icons/079c93f521434619a89b7d525b9643c7.png",
        "200": "https://images.cdn.kukufm.com/w:200/f:webp/q:85/https://s3.ap-south-1.amazonaws.com/kukufm/channel_icons/079c93f521434619a89b7d525b9643c7.png",
        "300": "https://images.cdn.kukufm.com/w:300/f:webp/q:85/https://s3.ap-south-1.amazonaws.com/kukufm/channel_icons/079c93f521434619a89b7d525b9643c7.png"
      },
      "n_likes": 0,
      "n_shares": 0,
      "n_plays": 31548,
      "n_listens": 31548,
      "n_comments": 5,
      "cover_type": null,
      "content": {
        "url": "https://d1l07mcd18xic4.cloudfront.net/audio/beab26ad-ac3a-46a1-ab12-a0af5d0c16ecfull.mp4",
        "hls_url": "https://d1l07mcd18xic4.cloudfront.net/audio/beab26ad-ac3a-46a1-ab12-a0af5d0c16ec.m3u8",
        "subtitle_url": "https://d1l07mcd18xic4.cloudfront.net/audio-transcripts/beab26ad-ac3a-46a1-ab12-a0af5d0c16ec.srt"
      },
      "dynamic_link": "https://applinks.kukufm.com/UXoNLbRhtrSNGF7u9",
      "is_premium": true,
      "is_play_locked": false,
      "is_locked": false,
      "is_fictional": false,
      "index": 1,
      "show_id": 201794,
      "season_no": 1,
      "is_demo_premium": true,
      "media_size": 6236908,
      "published_on": "2023-08-04T05:18:15.594728+00:00",
      "thumbnail_image": "https://images.cdn.kukufm.com/w:200/f:jpg/q:85/https://s3.ap-south-1.amazonaws.com/kukufm/channel_icons/079c93f521434619a89b7d525b9643c7.png"
    },
    "is_self": false,
    "ad_enabled": false,
    "can_download_all": true,
    "is_added": false,
    "genre": {
      "id": 4,
      "title": "धर्म",
      "slug": "religion",
      "uri": "app://app/genres/religion",
      "web_uri": "/genres/religion"
    },
    "credits": {
      "directors": [
        {
          "id": 28287293,
          "full_name": "Booshitha",
          "avatar": {
            "16": "https://images.cdn.kukufm.com/w:16/q:85/https://kukufm.s3.amazonaws.com/avatars/5c7aa638f3394365a3f7b449c36e3a39.png",
            "64": "https://images.cdn.kukufm.com/w:64/q:85/https://kukufm.s3.amazonaws.com/avatars/5c7aa638f3394365a3f7b449c36e3a39.png",
            "256": "https://images.cdn.kukufm.com/w:256/q:85/https://kukufm.s3.amazonaws.com/avatars/5c7aa638f3394365a3f7b449c36e3a39.png"
          },
          "n_followers": 1626,
          "contribution_type": "director",
          "is_primary_creator": true,
          "is_followed": false
        }
      ],
      "writers": [
        {
          "id": 9706266,
          "full_name": "Bharathi priyan",
          "avatar": {
            "16": "https://images.cdn.kukufm.com/w:16/q:85/https://kukufm.s3.amazonaws.com/avatars/27d81face6134838ab4824c566bbecb4.jpeg",
            "64": "https://images.cdn.kukufm.com/w:64/q:85/https://kukufm.s3.amazonaws.com/avatars/27d81face6134838ab4824c566bbecb4.jpeg",
            "256": "https://images.cdn.kukufm.com/w:256/q:85/https://kukufm.s3.amazonaws.com/avatars/27d81face6134838ab4824c566bbecb4.jpeg"
          },
          "n_followers": 643,
          "contribution_type": "writer",
          "is_primary_creator": true,
          "is_followed": false
        }
      ],
      "voice_artists": [
        {
          "id": 11209799,
          "full_name": "R. PRAVEENKUMAR",
          "avatar": {
            "16": "https://images.cdn.kukufm.com/w:16/q:85/https://kukufm.s3.amazonaws.com/avatars/edad9e198b274ef8b8ecbe64a638f880.jpeg",
            "64": "https://images.cdn.kukufm.com/w:64/q:85/https://kukufm.s3.amazonaws.com/avatars/edad9e198b274ef8b8ecbe64a638f880.jpeg",
            "256": "https://images.cdn.kukufm.com/w:256/q:85/https://kukufm.s3.amazonaws.com/avatars/edad9e198b274ef8b8ecbe64a638f880.jpeg"
          },
          "n_followers": 634,
          "contribution_type": "voice_artist",
          "is_primary_creator": false,
          "is_followed": false
        }
      ]
    },
    "media_size": 431341743,
    "is_play_locked": false,
    "hide_download_all_icon": null,
    "last_unlocked_episode_index": 1,
    "first_locked_episode_title": "1. Puranam sollapatta kadhai",
    "growth_engine_audio_cue_info": {},
    "social_proofing": {
      "review": null
    },
    "physical_book_data": {},
    "show_unlocked_nudge_text": "Unlocked with Premium"
  },
  "episodes": [
    {
      "id": 671129,
      "title": "Miga mukkiya moondravathu puranam",
      "slug": "vishnupuranam-intro",
      "status": "live",
      "image": "https://images.cdn.kukufm.com/f:webp/https://s3.ap-south-1.amazonaws.com/kukufm/channel_icons/079c93f521434619a89b7d525b9643c7.png",
      "original_image": "https://s3.ap-south-1.amazonaws.com/kukufm/channel_icons/079c93f521434619a89b7d525b9643c7.png",
      "duration_s": 265,
      "image_sizes": {
        "100": "https://images.cdn.kukufm.com/w:100/f:webp/q:85/https://s3.ap-south-1.amazonaws.com/kukufm/channel_icons/079c93f521434619a89b7d525b9643c7.png",
        "150": "https://images.cdn.kukufm.com/w:150/f:webp/q:85/https://s3.ap-south-1.amazonaws.com/kukufm/channel_icons/079c93f521434619a89b7d525b9643c7.png",
        "200": "https://images.cdn.kukufm.com/w:200/f:webp/q:85/https://s3.ap-south-1.amazonaws.com/kukufm/channel_icons/079c93f521434619a89b7d525b9643c7.png",
        "300": "https://images.cdn.kukufm.com/w:300/f:webp/q:85/https://s3.ap-south-1.amazonaws.com/kukufm/channel_icons/079c93f521434619a89b7d525b9643c7.png"
      },
      "n_likes": 0,
      "n_shares": 0,
      "n_plays": null,
      "n_listens": 31547,
      "n_comments": 5,
      "cover_type": null,
      "content": {
        "converted_hls_url": "https://kukufm.akamaized.net/audio/beab26ad-ac3a-46a1-ab12-a0af5d0c16ec.m3u8",
        "audio_128kb": "https://kukufm.akamaized.net/audio/beab26ad-ac3a-46a1-ab12-a0af5d0c16ec128kb.m3u8",
        "audio_64kb": "https://kukufm.akamaized.net/audio/beab26ad-ac3a-46a1-ab12-a0af5d0c16ec64kb.m3u8",
        "audio_24kb": "https://kukufm.akamaized.net/audio/beab26ad-ac3a-46a1-ab12-a0af5d0c16ec24kb.m3u8"
      },
      "dynamic_link": "https://applinks.kukufm.com/UXoNLbRhtrSNGF7u9",
      "is_premium": true,
      "is_play_locked": false,
      "is_locked": false,
      "is_fictional": false,
      "index": 1,
      "show_id": 201794,
      "season_no": 1,
      "is_demo_premium": true,
      "media_size": 6236908,
      "published_on": "2023-08-04T05:18:15.594728+00:00",
      "thumbnail_image": "https://images.cdn.kukufm.com/w:200/f:jpg/q:85/https://s3.ap-south-1.amazonaws.com/kukufm/channel_icons/079c93f521434619a89b7d525b9643c7.png",
      "web_uri": "/episode/vishnupuranam-intro",
      "view_type": "default",
      "unlocking_nudge_text": "",
      "unlocking_nudge_text_v2": "",
      "has_srt": false,
      "has_liked": false,
      "seek_position": 0,
      "can_download": true,
      "is_downloaded": false,
      "is_self": false,
      "unlock_type": "subscription",
      "transcript": {}
    },
    {
      "id": 671130,
      "title": "1. Puranam sollapatta kadhai",
      "slug": "vishnupuranam-ep-1",
      "status": "live",
      "image": "https://images.cdn.kukufm.com/f:webp/https://s3.ap-south-1.amazonaws.com/kukufm/channel_icons/079c93f521434619a89b7d525b9643c7.png",
      "original_image": "https://s3.ap-south-1.amazonaws.com/kukufm/channel_icons/079c93f521434619a89b7d525b9643c7.png",
      "duration_s": 634,
      "image_sizes": {
        "100": "https://images.cdn.kukufm.com/w:100/f:webp/q:85/https://s3.ap-south-1.amazonaws.com/kukufm/channel_icons/079c93f521434619a89b7d525b9643c7.png",
        "150": "https://images.cdn.kukufm.com/w:150/f:webp/q:85/https://s3.ap-south-1.amazonaws.com/kukufm/channel_icons/079c93f521434619a89b7d525b9643c7.png",
        "200": "https://images.cdn.kukufm.com/w:200/f:webp/q:85/https://s3.ap-south-1.amazonaws.com/kukufm/channel_icons/079c93f521434619a89b7d525b9643c7.png",
        "300": "https://images.cdn.kukufm.com/w:300/f:webp/q:85/https://s3.ap-south-1.amazonaws.com/kukufm/channel_icons/079c93f521434619a89b7d525b9643c7.png"
      },
      "n_likes": 0,
      "n_shares": 0,
      "n_plays": null,
      "n_listens": 15012,
      "n_comments": 6,
      "cover_type": null,
      "content": {
        "converted_hls_url": "https://kukufm.akamaized.net/audio/abcb78c4-2dda-4c55-a773-6e1be32bec4e.m3u8",
        "audio_128kb": "https://kukufm.akamaized.net/audio/abcb78c4-2dda-4c55-a773-6e1be32bec4e128kb.m3u8",
        "audio_64kb": "https://kukufm.akamaized.net/audio/abcb78c4-2dda-4c55-a773-6e1be32bec4e64kb.m3u8",
        "audio_24kb": "https://kukufm.akamaized.net/audio/abcb78c4-2dda-4c55-a773-6e1be32bec4e24kb.m3u8"
      },
      "dynamic_link": "https://applinks.kukufm.com/i5beymGhZzqDqXPE8",
      "is_premium": true,
      "is_play_locked": false,
      "is_locked": true,
      "is_fictional": false,
      "index": 2,
      "show_id": 201794,
      "season_no": 1,
      "is_demo_premium": false,
      "is_free_unlocked": true,
      "media_size": 13337750,
      "published_on": "2023-08-04T05:18:15.594728+00:00",
      "thumbnail_image": "https://images.cdn.kukufm.com/w:200/f:jpg/q:85/https://s3.ap-south-1.amazonaws.com/kukufm/channel_icons/079c93f521434619a89b7d525b9643c7.png",
      "web_uri": "/episode/vishnupuranam-ep-1",
      "view_type": "default",
      "unlocking_nudge_text": "",
      "unlocking_nudge_text_v2": "",
      "has_srt": false,
      "has_liked": false,
      "seek_position": 0,
      "can_download": true,
      "is_downloaded": false,
      "is_self": false,
      "unlock_type": "subscription",
      "transcript": {}
    },
    {
      "id": 671131,
      "title": "2. varaha avatharam varai",
      "slug": "vishnupuranam-ep-2",
      "status": "live",
      "image": "https://images.cdn.kukufm.com/f:webp/https://s3.ap-south-1.amazonaws.com/kukufm/channel_icons/079c93f521434619a89b7d525b9643c7.png",
      "original_image": "https://s3.ap-south-1.amazonaws.com/kukufm/channel_icons/079c93f521434619a89b7d525b9643c7.png",
      "duration_s": 898,
      "image_sizes": {
        "100": "https://images.cdn.kukufm.com/w:100/f:webp/q:85/https://s3.ap-south-1.amazonaws.com/kukufm/channel_icons/079c93f521434619a89b7d525b9643c7.png",
        "150": "https://images.cdn.kukufm.com/w:150/f:webp/q:85/https://s3.ap-south-1.amazonaws.com/kukufm/channel_icons/079c93f521434619a89b7d525b9643c7.png",
        "200": "https://images.cdn.kukufm.com/w:200/f:webp/q:85/https://s3.ap-south-1.amazonaws.com/kukufm/channel_icons/079c93f521434619a89b7d525b9643c7.png",
        "300": "https://images.cdn.kukufm.com/w:300/f:webp/q:85/https://s3.ap-south-1.amazonaws.com/kukufm/channel_icons/079c93f521434619a89b7d525b9643c7.png"
      },
      "n_likes": 0,
      "n_shares": 0,
      "n_plays": null,
      "n_listens": 10581,
      "n_comments": 1,
      "cover_type": null,
      "content": {
        "converted_hls_url": "https://kukufm.akamaized.net/audio/48d0c7da-adb6-4063-8319-281d03e7115b.m3u8",
        "audio_128kb": "https://kukufm.akamaized.net/audio/48d0c7da-adb6-4063-8319-281d03e7115b128kb.m3u8",
        "audio_64kb": "https://kukufm.akamaized.net/audio/48d0c7da-adb6-4063-8319-281d03e7115b64kb.m3u8",
        "audio_24kb": "https://kukufm.akamaized.net/audio/48d0c7da-adb6-4063-8319-281d03e7115b24kb.m3u8"
      },
      "dynamic_link": "https://applinks.kukufm.com/n5jABDwJ5ywfvwaF8",
      "is_premium": true,
      "is_play_locked": false,
      "is_locked": true,
      "is_fictional": false,
      "index": 3,
      "show_id": 201794,
      "season_no": 1,
      "is_demo_premium": false,
      "is_free_unlocked": true,
      "media_size": 18852009,
      "published_on": "2023-08-04T05:18:15.594728+00:00",
      "thumbnail_image": "https://images.cdn.kukufm.com/w:200/f:jpg/q:85/https://s3.ap-south-1.amazonaws.com/kukufm/channel_icons/079c93f521434619a89b7d525b9643c7.png",
      "web_uri": "/episode/vishnupuranam-ep-2",
      "view_type": "default",
      "unlocking_nudge_text": "",
      "unlocking_nudge_text_v2": "",
      "has_srt": false,
      "has_liked": false,
      "seek_position": 0,
      "can_download": true,
      "is_downloaded": false,
      "is_self": false,
      "unlock_type": "subscription",
      "transcript": {}
    },
    {
      "id": 671132,
      "title": "3. Padaigal",
      "slug": "vishnupuranam-ep-3",
      "status": "live",
      "image": "https://images.cdn.kukufm.com/f:webp/https://s3.ap-south-1.amazonaws.com/kukufm/channel_icons/079c93f521434619a89b7d525b9643c7.png",
      "original_image": "https://s3.ap-south-1.amazonaws.com/kukufm/channel_icons/079c93f521434619a89b7d525b9643c7.png",
      "duration_s": 525,
      "image_sizes": {
        "100": "https://images.cdn.kukufm.com/w:100/f:webp/q:85/https://s3.ap-south-1.amazonaws.com/kukufm/channel_icons/079c93f521434619a89b7d525b9643c7.png",
        "150": "https://images.cdn.kukufm.com/w:150/f:webp/q:85/https://s3.ap-south-1.amazonaws.com/kukufm/channel_icons/079c93f521434619a89b7d525b9643c7.png",
        "200": "https://images.cdn.kukufm.com/w:200/f:webp/q:85/https://s3.ap-south-1.amazonaws.com/kukufm/channel_icons/079c93f521434619a89b7d525b9643c7.png",
        "300": "https://images.cdn.kukufm.com/w:300/f:webp/q:85/https://s3.ap-south-1.amazonaws.com/kukufm/channel_icons/079c93f521434619a89b7d525b9643c7.png"
      },
      "n_likes": 0,
      "n_shares": 0,
      "n_plays": null,
      "n_listens": 6488,
      "n_comments": 0,
      "cover_type": null,
      "content": {
        "converted_hls_url": "https://kukufm.akamaized.net/audio/3b11df06-f902-4baa-b721-9eea73340fa1.m3u8",
        "audio_128kb": "https://kukufm.akamaized.net/audio/3b11df06-f902-4baa-b721-9eea73340fa1128kb.m3u8",
        "audio_64kb": "https://kukufm.akamaized.net/audio/3b11df06-f902-4baa-b721-9eea73340fa164kb.m3u8",
        "audio_24kb": "https://kukufm.akamaized.net/audio/3b11df06-f902-4baa-b721-9eea73340fa124kb.m3u8"
      },
      "dynamic_link": "https://applinks.kukufm.com/YZQrxHejwTnjFYSp6",
      "is_premium": true,
      "is_play_locked": false,
      "is_locked": true,
      "is_fictional": false,
      "index": 4,
      "show_id": 201794,
      "season_no": 1,
      "is_demo_premium": false,
      "is_free_unlocked": true,
      "media_size": 11513050,
      "published_on": "2023-08-04T05:18:15.594728+00:00",
      "thumbnail_image": "https://images.cdn.kukufm.com/w:200/f:jpg/q:85/https://s3.ap-south-1.amazonaws.com/kukufm/channel_icons/079c93f521434619a89b7d525b9643c7.png",
      "web_uri": "/episode/vishnupuranam-ep-3",
      "view_type": "default",
      "unlocking_nudge_text": "",
      "unlocking_nudge_text_v2": "",
      "has_srt": false,
      "has_liked": false,
      "seek_position": 0,
      "can_download": true,
      "is_downloaded": false,
      "is_self": false,
      "unlock_type": "subscription",
      "transcript": {}
    },
    {
      "id": 671133,
      "title": "4. Uruva sarithiram",
      "slug": "vishnupuranam-ep-04-new",
      "status": "live",
      "image": "https://images.cdn.kukufm.com/f:webp/https://s3.ap-south-1.amazonaws.com/kukufm/channel_icons/079c93f521434619a89b7d525b9643c7.png",
      "original_image": "https://s3.ap-south-1.amazonaws.com/kukufm/channel_icons/079c93f521434619a89b7d525b9643c7.png",
      "duration_s": 1058,
      "image_sizes": {
        "100": "https://images.cdn.kukufm.com/w:100/f:webp/q:85/https://s3.ap-south-1.amazonaws.com/kukufm/channel_icons/079c93f521434619a89b7d525b9643c7.png",
        "150": "https://images.cdn.kukufm.com/w:150/f:webp/q:85/https://s3.ap-south-1.amazonaws.com/kukufm/channel_icons/079c93f521434619a89b7d525b9643c7.png",
        "200": "https://images.cdn.kukufm.com/w:200/f:webp/q:85/https://s3.ap-south-1.amazonaws.com/kukufm/channel_icons/079c93f521434619a89b7d525b9643c7.png",
        "300": "https://images.cdn.kukufm.com/w:300/f:webp/q:85/https://s3.ap-south-1.amazonaws.com/kukufm/channel_icons/079c93f521434619a89b7d525b9643c7.png"
      },
      "n_likes": 0,
      "n_shares": 0,
      "n_plays": null,
      "n_listens": 6902,
      "n_comments": 1,
      "cover_type": null,
      "content": {
        "converted_hls_url": "https://kukufm.akamaized.net/audio/078ba959-4778-424b-979a-5b9c4b07897f.m3u8",
        "audio_128kb": "https://kukufm.akamaized.net/audio/078ba959-4778-424b-979a-5b9c4b07897f128kb.m3u8",
        "audio_64kb": "https://kukufm.akamaized.net/audio/078ba959-4778-424b-979a-5b9c4b07897f64kb.m3u8",
        "audio_24kb": "https://kukufm.akamaized.net/audio/078ba959-4778-424b-979a-5b9c4b07897f24kb.m3u8"
      },
      "dynamic_link": "https://applinks.kukufm.com/sHAHyGvuJWGCoeie6",
      "is_premium": true,
      "is_play_locked": false,
      "is_locked": true,
      "is_fictional": false,
      "index": 5,
      "show_id": 201794,
      "season_no": 1,
      "is_demo_premium": false,
      "is_free_unlocked": true,
      "media_size": 22268601,
      "published_on": "2023-08-04T05:18:15.594728+00:00",
      "thumbnail_image": "https://images.cdn.kukufm.com/w:200/f:jpg/q:85/https://s3.ap-south-1.amazonaws.com/kukufm/channel_icons/079c93f521434619a89b7d525b9643c7.png",
      "web_uri": "/episode/vishnupuranam-ep-04-new",
      "view_type": "default",
      "unlocking_nudge_text": "",
      "unlocking_nudge_text_v2": "",
      "has_srt": false,
      "has_liked": false,
      "seek_position": 0,
      "can_download": true,
      "is_downloaded": false,
      "is_self": false,
      "unlock_type": "subscription",
      "transcript": {}
    },
    {
      "id": 671134,
      "title": "5. Sarithiram",
      "slug": "vishnupuranam-ep-5",
      "status": "live",
      "image": "https://images.cdn.kukufm.com/f:webp/https://s3.ap-south-1.amazonaws.com/kukufm/channel_icons/079c93f521434619a89b7d525b9643c7.png",
      "original_image": "https://s3.ap-south-1.amazonaws.com/kukufm/channel_icons/079c93f521434619a89b7d525b9643c7.png",
      "duration_s": 592,
      "image_sizes": {
        "100": "https://images.cdn.kukufm.com/w:100/f:webp/q:85/https://s3.ap-south-1.amazonaws.com/kukufm/channel_icons/079c93f521434619a89b7d525b9643c7.png",
        "150": "https://images.cdn.kukufm.com/w:150/f:webp/q:85/https://s3.ap-south-1.amazonaws.com/kukufm/channel_icons/079c93f521434619a89b7d525b9643c7.png",
        "200": "https://images.cdn.kukufm.com/w:200/f:webp/q:85/https://s3.ap-south-1.amazonaws.com/kukufm/channel_icons/079c93f521434619a89b7d525b9643c7.png",
        "300": "https://images.cdn.kukufm.com/w:300/f:webp/q:85/https://s3.ap-south-1.amazonaws.com/kukufm/channel_icons/079c93f521434619a89b7d525b9643c7.png"
      },
      "n_likes": 0,
      "n_shares": 0,
      "n_plays": null,
      "n_listens": 4797,
      "n_comments": 0,
      "cover_type": null,
      "content": {
        "converted_hls_url": "https://kukufm.akamaized.net/audio/e743ccb8-5010-4165-9f81-fdef4cf8543f.m3u8",
        "audio_128kb": "https://kukufm.akamaized.net/audio/e743ccb8-5010-4165-9f81-fdef4cf8543f128kb.m3u8",
        "audio_64kb": "https://kukufm.akamaized.net/audio/e743ccb8-5010-4165-9f81-fdef4cf8543f64kb.m3u8",
        "audio_24kb": "https://kukufm.akamaized.net/audio/e743ccb8-5010-4165-9f81-fdef4cf8543f24kb.m3u8"
      },
      "dynamic_link": "https://applinks.kukufm.com/3foce1jBznbgpXWD8",
      "is_premium": true,
      "is_play_locked": false,
      "is_locked": true,
      "is_fictional": false,
      "index": 6,
      "show_id": 201794,
      "season_no": 1,
      "is_demo_premium": false,
      "is_free_unlocked": true,
      "media_size": 12461519,
      "published_on": "2023-08-04T05:18:15.594728+00:00",
      "thumbnail_image": "https://images.cdn.kukufm.com/w:200/f:jpg/q:85/https://s3.ap-south-1.amazonaws.com/kukufm/channel_icons/079c93f521434619a89b7d525b9643c7.png",
      "web_uri": "/episode/vishnupuranam-ep-5",
      "view_type": "default",
      "unlocking_nudge_text": "",
      "unlocking_nudge_text_v2": "",
      "has_srt": false,
      "has_liked": false,
      "seek_position": 0,
      "can_download": true,
      "is_downloaded": false,
      "is_self": false,
      "unlock_type": "subscription",
      "transcript": {}
    },
    {
      "id": 671135,
      "title": "6. Kandu maharishi",
      "slug": "vishnupuranam-ep-6",
      "status": "live",
      "image": "https://images.cdn.kukufm.com/f:webp/https://s3.ap-south-1.amazonaws.com/kukufm/channel_icons/079c93f521434619a89b7d525b9643c7.png",
      "original_image": "https://s3.ap-south-1.amazonaws.com/kukufm/channel_icons/079c93f521434619a89b7d525b9643c7.png",
      "duration_s": 916,
      "image_sizes": {
        "100": "https://images.cdn.kukufm.com/w:100/f:webp/q:85/https://s3.ap-south-1.amazonaws.com/kukufm/channel_icons/079c93f521434619a89b7d525b9643c7.png",
        "150": "https://images.cdn.kukufm.com/w:150/f:webp/q:85/https://s3.ap-south-1.amazonaws.com/kukufm/channel_icons/079c93f521434619a89b7d525b9643c7.png",
        "200": "https://images.cdn.kukufm.com/w:200/f:webp/q:85/https://s3.ap-south-1.amazonaws.com/kukufm/channel_icons/079c93f521434619a89b7d525b9643c7.png",
        "300": "https://images.cdn.kukufm.com/w:300/f:webp/q:85/https://s3.ap-south-1.amazonaws.com/kukufm/channel_icons/079c93f521434619a89b7d525b9643c7.png"
      },
      "n_likes": 0,
      "n_shares": 0,
      "n_plays": null,
      "n_listens": 4443,
      "n_comments": 4,
      "cover_type": null,
      "content": {
        "converted_hls_url": "https://kukufm.akamaized.net/audio/0705bf41-1cd4-4947-a823-d91a99bc6f1b.m3u8",
        "audio_128kb": "https://kukufm.akamaized.net/audio/0705bf41-1cd4-4947-a823-d91a99bc6f1b128kb.m3u8",
        "audio_64kb": "https://kukufm.akamaized.net/audio/0705bf41-1cd4-4947-a823-d91a99bc6f1b64kb.m3u8",
        "audio_24kb": "https://kukufm.akamaized.net/audio/0705bf41-1cd4-4947-a823-d91a99bc6f1b24kb.m3u8"
      },
      "dynamic_link": "https://applinks.kukufm.com/o2BF94xXWDezJu3w9",
      "is_premium": true,
      "is_play_locked": false,
      "is_locked": true,
      "is_fictional": false,
      "index": 7,
      "show_id": 201794,
      "season_no": 1,
      "is_demo_premium": false,
      "is_free_unlocked": true,
      "media_size": 19126310,
      "published_on": "2023-08-04T05:18:15.594728+00:00",
      "thumbnail_image": "https://images.cdn.kukufm.com/w:200/f:jpg/q:85/https://s3.ap-south-1.amazonaws.com/kukufm/channel_icons/079c93f521434619a89b7d525b9643c7.png",
      "web_uri": "/episode/vishnupuranam-ep-6",
      "view_type": "default",
      "unlocking_nudge_text": "",
      "unlocking_nudge_text_v2": "",
      "has_srt": false,
      "has_liked": false,
      "seek_position": 0,
      "can_download": true,
      "is_downloaded": false,
      "is_self": false,
      "unlock_type": "subscription",
      "transcript": {}
    },
    {
      "id": 671136,
      "title": "7. Kasiba munivar",
      "slug": "vishnupuranam-ep-7",
      "status": "live",
      "image": "https://images.cdn.kukufm.com/f:webp/https://s3.ap-south-1.amazonaws.com/kukufm/channel_icons/079c93f521434619a89b7d525b9643c7.png",
      "original_image": "https://s3.ap-south-1.amazonaws.com/kukufm/channel_icons/079c93f521434619a89b7d525b9643c7.png",
      "duration_s": 594,
      "image_sizes": {
        "100": "https://images.cdn.kukufm.com/w:100/f:webp/q:85/https://s3.ap-south-1.amazonaws.com/kukufm/channel_icons/079c93f521434619a89b7d525b9643c7.png",
        "150": "https://images.cdn.kukufm.com/w:150/f:webp/q:85/https://s3.ap-south-1.amazonaws.com/kukufm/channel_icons/079c93f521434619a89b7d525b9643c7.png",
        "200": "https://images.cdn.kukufm.com/w:200/f:webp/q:85/https://s3.ap-south-1.amazonaws.com/kukufm/channel_icons/079c93f521434619a89b7d525b9643c7.png",
        "300": "https://images.cdn.kukufm.com/w:300/f:webp/q:85/https://s3.ap-south-1.amazonaws.com/kukufm/channel_icons/079c93f521434619a89b7d525b9643c7.png"
      },
      "n_likes": 0,
      "n_shares": 0,
      "n_plays": null,
      "n_listens": 3587,
      "n_comments": 0,
      "cover_type": null,
      "content": {
        "converted_hls_url": "https://kukufm.akamaized.net/audio/1aac4784-0dfb-4216-abe5-ef65df26f8bb.m3u8",
        "audio_128kb": "https://kukufm.akamaized.net/audio/1aac4784-0dfb-4216-abe5-ef65df26f8bb128kb.m3u8",
        "audio_64kb": "https://kukufm.akamaized.net/audio/1aac4784-0dfb-4216-abe5-ef65df26f8bb64kb.m3u8",
        "audio_24kb": "https://kukufm.akamaized.net/audio/1aac4784-0dfb-4216-abe5-ef65df26f8bb24kb.m3u8"
      },
      "dynamic_link": "https://applinks.kukufm.com/tQGNWj18hAaHABVF8",
      "is_premium": true,
      "is_play_locked": false,
      "is_locked": true,
      "is_fictional": false,
      "index": 8,
      "show_id": 201794,
      "season_no": 1,
      "is_demo_premium": false,
      "is_free_unlocked": true,
      "media_size": 12794911,
      "published_on": "2023-08-04T05:18:15.594728+00:00",
      "thumbnail_image": "https://images.cdn.kukufm.com/w:200/f:jpg/q:85/https://s3.ap-south-1.amazonaws.com/kukufm/channel_icons/079c93f521434619a89b7d525b9643c7.png",
      "web_uri": "/episode/vishnupuranam-ep-7",
      "view_type": "default",
      "unlocking_nudge_text": "",
      "unlocking_nudge_text_v2": "",
      "has_srt": false,
      "has_liked": false,
      "seek_position": 0,
      "can_download": true,
      "is_downloaded": false,
      "is_self": false,
      "unlock_type": "subscription",
      "transcript": {}
    },
    {
      "id": 671137,
      "title": "8. Mano'vin Kudumbam",
      "slug": "vishnupuranam-ep-8",
      "status": "live",
      "image": "https://images.cdn.kukufm.com/f:webp/https://s3.ap-south-1.amazonaws.com/kukufm/channel_icons/079c93f521434619a89b7d525b9643c7.png",
      "original_image": "https://s3.ap-south-1.amazonaws.com/kukufm/channel_icons/079c93f521434619a89b7d525b9643c7.png",
      "duration_s": 674,
      "image_sizes": {
        "100": "https://images.cdn.kukufm.com/w:100/f:webp/q:85/https://s3.ap-south-1.amazonaws.com/kukufm/channel_icons/079c93f521434619a89b7d525b9643c7.png",
        "150": "https://images.cdn.kukufm.com/w:150/f:webp/q:85/https://s3.ap-south-1.amazonaws.com/kukufm/channel_icons/079c93f521434619a89b7d525b9643c7.png",
        "200": "https://images.cdn.kukufm.com/w:200/f:webp/q:85/https://s3.ap-south-1.amazonaws.com/kukufm/channel_icons/079c93f521434619a89b7d525b9643c7.png",
        "300": "https://images.cdn.kukufm.com/w:300/f:webp/q:85/https://s3.ap-south-1.amazonaws.com/kukufm/channel_icons/079c93f521434619a89b7d525b9643c7.png"
      },
      "n_likes": 0,
      "n_shares": 0,
      "n_plays": null,
      "n_listens": 3210,
      "n_comments": 0,
      "cover_type": null,
      "content": {
        "converted_hls_url": "https://kukufm.akamaized.net/audio/39cccb71-12d0-411c-9ce7-c7f311b37859.m3u8",
        "audio_128kb": "https://kukufm.akamaized.net/audio/39cccb71-12d0-411c-9ce7-c7f311b37859128kb.m3u8",
        "audio_64kb": "https://kukufm.akamaized.net/audio/39cccb71-12d0-411c-9ce7-c7f311b3785964kb.m3u8",
        "audio_24kb": "https://kukufm.akamaized.net/audio/39cccb71-12d0-411c-9ce7-c7f311b3785924kb.m3u8"
      },
      "dynamic_link": "https://applinks.kukufm.com/P6UWPJ8kxzaLgfuP7",
      "is_premium": true,
      "is_play_locked": false,
      "is_locked": true,
      "is_fictional": false,
      "index": 9,
      "show_id": 201794,
      "season_no": 1,
      "is_demo_premium": false,
      "is_free_unlocked": true,
      "media_size": 14050763,
      "published_on": "2023-08-04T05:18:15.594728+00:00",
      "thumbnail_image": "https://images.cdn.kukufm.com/w:200/f:jpg/q:85/https://s3.ap-south-1.amazonaws.com/kukufm/channel_icons/079c93f521434619a89b7d525b9643c7.png",
      "web_uri": "/episode/vishnupuranam-ep-8",
      "view_type": "default",
      "unlocking_nudge_text": "",
      "unlocking_nudge_text_v2": "",
      "has_srt": false,
      "has_liked": false,
      "seek_position": 0,
      "can_download": true,
      "is_downloaded": false,
      "is_self": false,
      "unlock_type": "subscription",
      "transcript": {}
    },
    {
      "id": 671138,
      "title": "9. Baratham",
      "slug": "vishnupuranam-ep-9",
      "status": "live",
      "image": "https://images.cdn.kukufm.com/f:webp/https://s3.ap-south-1.amazonaws.com/kukufm/channel_icons/079c93f521434619a89b7d525b9643c7.png",
      "original_image": "https://s3.ap-south-1.amazonaws.com/kukufm/channel_icons/079c93f521434619a89b7d525b9643c7.png",
      "duration_s": 638,
      "image_sizes": {
        "100": "https://images.cdn.kukufm.com/w:100/f:webp/q:85/https://s3.ap-south-1.amazonaws.com/kukufm/channel_icons/079c93f521434619a89b7d525b9643c7.png",
        "150": "https://images.cdn.kukufm.com/w:150/f:webp/q:85/https://s3.ap-south-1.amazonaws.com/kukufm/channel_icons/079c93f521434619a89b7d525b9643c7.png",
        "200": "https://images.cdn.kukufm.com/w:200/f:webp/q:85/https://s3.ap-south-1.amazonaws.com/kukufm/channel_icons/079c93f521434619a89b7d525b9643c7.png",
        "300": "https://images.cdn.kukufm.com/w:300/f:webp/q:85/https://s3.ap-south-1.amazonaws.com/kukufm/channel_icons/079c93f521434619a89b7d525b9643c7.png"
      },
      "n_likes": 0,
      "n_shares": 0,
      "n_plays": null,
      "n_listens": 2956,
      "n_comments": 0,
      "cover_type": null,
      "content": {
        "converted_hls_url": "https://kukufm.akamaized.net/audio/c8d26d6c-3370-49e8-a0b3-0fa02202969b.m3u8",
        "audio_128kb": "https://kukufm.akamaized.net/audio/c8d26d6c-3370-49e8-a0b3-0fa02202969b128kb.m3u8",
        "audio_64kb": "https://kukufm.akamaized.net/audio/c8d26d6c-3370-49e8-a0b3-0fa02202969b64kb.m3u8",
        "audio_24kb": "https://kukufm.akamaized.net/audio/c8d26d6c-3370-49e8-a0b3-0fa02202969b24kb.m3u8"
      },
      "dynamic_link": "https://applinks.kukufm.com/TNcwpJfrsxYGjmS9A",
      "is_premium": true,
      "is_play_locked": false,
      "is_locked": true,
      "is_fictional": false,
      "index": 10,
      "show_id": 201794,
      "season_no": 1,
      "is_demo_premium": false,
      "is_free_unlocked": true,
      "media_size": 13629862,
      "published_on": "2023-08-04T05:18:15.594728+00:00",
      "thumbnail_image": "https://images.cdn.kukufm.com/w:200/f:jpg/q:85/https://s3.ap-south-1.amazonaws.com/kukufm/channel_icons/079c93f521434619a89b7d525b9643c7.png",
      "web_uri": "/episode/vishnupuranam-ep-9",
      "view_type": "default",
      "unlocking_nudge_text": "",
      "unlocking_nudge_text_v2": "",
      "has_srt": false,
      "has_liked": false,
      "seek_position": 0,
      "can_download": true,
      "is_downloaded": false,
      "is_self": false,
      "unlock_type": "subscription",
      "transcript": {}
    },
    {
      "id": 671139,
      "title": "10. Palvagai ulagangal",
      "slug": "vishnupuranam-ep-10",
      "status": "live",
      "image": "https://images.cdn.kukufm.com/f:webp/https://s3.ap-south-1.amazonaws.com/kukufm/channel_icons/079c93f521434619a89b7d525b9643c7.png",
      "original_image": "https://s3.ap-south-1.amazonaws.com/kukufm/channel_icons/079c93f521434619a89b7d525b9643c7.png",
      "duration_s": 912,
      "image_sizes": {
        "100": "https://images.cdn.kukufm.com/w:100/f:webp/q:85/https://s3.ap-south-1.amazonaws.com/kukufm/channel_icons/079c93f521434619a89b7d525b9643c7.png",
        "150": "https://images.cdn.kukufm.com/w:150/f:webp/q:85/https://s3.ap-south-1.amazonaws.com/kukufm/channel_icons/079c93f521434619a89b7d525b9643c7.png",
        "200": "https://images.cdn.kukufm.com/w:200/f:webp/q:85/https://s3.ap-south-1.amazonaws.com/kukufm/channel_icons/079c93f521434619a89b7d525b9643c7.png",
        "300": "https://images.cdn.kukufm.com/w:300/f:webp/q:85/https://s3.ap-south-1.amazonaws.com/kukufm/channel_icons/079c93f521434619a89b7d525b9643c7.png"
      },
      "n_likes": 0,
      "n_shares": 0,
      "n_plays": null,
      "n_listens": 2945,
      "n_comments": 0,
      "cover_type": null,
      "content": {
        "converted_hls_url": "https://kukufm.akamaized.net/audio/9c02077a-0513-4d9c-abe3-a414d4268008.m3u8",
        "audio_128kb": "https://kukufm.akamaized.net/audio/9c02077a-0513-4d9c-abe3-a414d4268008128kb.m3u8",
        "audio_64kb": "https://kukufm.akamaized.net/audio/9c02077a-0513-4d9c-abe3-a414d426800864kb.m3u8",
        "audio_24kb": "https://kukufm.akamaized.net/audio/9c02077a-0513-4d9c-abe3-a414d426800824kb.m3u8"
      },
      "dynamic_link": "https://applinks.kukufm.com/9Qord9E97k2XuhYk9",
      "is_premium": true,
      "is_play_locked": false,
      "is_locked": true,
      "is_fictional": false,
      "index": 11,
      "show_id": 201794,
      "season_no": 1,
      "is_demo_premium": false,
      "is_free_unlocked": true,
      "media_size": 19163957,
      "published_on": "2023-08-04T05:18:15.594728+00:00",
      "thumbnail_image": "https://images.cdn.kukufm.com/w:200/f:jpg/q:85/https://s3.ap-south-1.amazonaws.com/kukufm/channel_icons/079c93f521434619a89b7d525b9643c7.png",
      "web_uri": "/episode/vishnupuranam-ep-10",
      "view_type": "default",
      "unlocking_nudge_text": "",
      "unlocking_nudge_text_v2": "",
      "has_srt": false,
      "has_liked": false,
      "seek_position": 0,
      "can_download": true,
      "is_downloaded": false,
      "is_self": false,
      "unlock_type": "subscription",
      "transcript": {}
    },
    {
      "id": 671140,
      "title": "11. Navagiragangal",
      "slug": "vishnupuranam-ep-11",
      "status": "live",
      "image": "https://images.cdn.kukufm.com/f:webp/https://s3.ap-south-1.amazonaws.com/kukufm/channel_icons/079c93f521434619a89b7d525b9643c7.png",
      "original_image": "https://s3.ap-south-1.amazonaws.com/kukufm/channel_icons/079c93f521434619a89b7d525b9643c7.png",
      "duration_s": 783,
      "image_sizes": {
        "100": "https://images.cdn.kukufm.com/w:100/f:webp/q:85/https://s3.ap-south-1.amazonaws.com/kukufm/channel_icons/079c93f521434619a89b7d525b9643c7.png",
        "150": "https://images.cdn.kukufm.com/w:150/f:webp/q:85/https://s3.ap-south-1.amazonaws.com/kukufm/channel_icons/079c93f521434619a89b7d525b9643c7.png",
        "200": "https://images.cdn.kukufm.com/w:200/f:webp/q:85/https://s3.ap-south-1.amazonaws.com/kukufm/channel_icons/079c93f521434619a89b7d525b9643c7.png",
        "300": "https://images.cdn.kukufm.com/w:300/f:webp/q:85/https://s3.ap-south-1.amazonaws.com/kukufm/channel_icons/079c93f521434619a89b7d525b9643c7.png"
      },
      "n_likes": 0,
      "n_shares": 0,
      "n_plays": null,
      "n_listens": 3047,
      "n_comments": 0,
      "cover_type": null,
      "content": {
        "converted_hls_url": "https://kukufm.akamaized.net/audio/d226edf2-22e1-4594-912d-56647b22920b.m3u8",
        "audio_128kb": "https://kukufm.akamaized.net/audio/d226edf2-22e1-4594-912d-56647b22920b128kb.m3u8",
        "audio_64kb": "https://kukufm.akamaized.net/audio/d226edf2-22e1-4594-912d-56647b22920b64kb.m3u8",
        "audio_24kb": "https://kukufm.akamaized.net/audio/d226edf2-22e1-4594-912d-56647b22920b24kb.m3u8"
      },
      "dynamic_link": "https://applinks.kukufm.com/ZPdwQShhESYUMxRZ8",
      "is_premium": true,
      "is_play_locked": false,
      "is_locked": true,
      "is_fictional": false,
      "index": 12,
      "show_id": 201794,
      "season_no": 1,
      "is_demo_premium": false,
      "is_free_unlocked": true,
      "media_size": 16361509,
      "published_on": "2023-08-04T05:18:15.594728+00:00",
      "thumbnail_image": "https://images.cdn.kukufm.com/w:200/f:jpg/q:85/https://s3.ap-south-1.amazonaws.com/kukufm/channel_icons/079c93f521434619a89b7d525b9643c7.png",
      "web_uri": "/episode/vishnupuranam-ep-11",
      "view_type": "default",
      "unlocking_nudge_text": "",
      "unlocking_nudge_text_v2": "",
      "has_srt": false,
      "has_liked": false,
      "seek_position": 0,
      "can_download": true,
      "is_downloaded": false,
      "is_self": false,
      "unlock_type": "subscription",
      "transcript": {}
    },
    {
      "id": 671141,
      "title": "12. Ooh gurudev !",
      "slug": "vishnupuranam-ep-12",
      "status": "live",
      "image": "https://images.cdn.kukufm.com/f:webp/https://s3.ap-south-1.amazonaws.com/kukufm/channel_icons/079c93f521434619a89b7d525b9643c7.png",
      "original_image": "https://s3.ap-south-1.amazonaws.com/kukufm/channel_icons/079c93f521434619a89b7d525b9643c7.png",
      "duration_s": 809,
      "image_sizes": {
        "100": "https://images.cdn.kukufm.com/w:100/f:webp/q:85/https://s3.ap-south-1.amazonaws.com/kukufm/channel_icons/079c93f521434619a89b7d525b9643c7.png",
        "150": "https://images.cdn.kukufm.com/w:150/f:webp/q:85/https://s3.ap-south-1.amazonaws.com/kukufm/channel_icons/079c93f521434619a89b7d525b9643c7.png",
        "200": "https://images.cdn.kukufm.com/w:200/f:webp/q:85/https://s3.ap-south-1.amazonaws.com/kukufm/channel_icons/079c93f521434619a89b7d525b9643c7.png",
        "300": "https://images.cdn.kukufm.com/w:300/f:webp/q:85/https://s3.ap-south-1.amazonaws.com/kukufm/channel_icons/079c93f521434619a89b7d525b9643c7.png"
      },
      "n_likes": 0,
      "n_shares": 0,
      "n_plays": null,
      "n_listens": 2299,
      "n_comments": 0,
      "cover_type": null,
      "content": {
        "converted_hls_url": "https://kukufm.akamaized.net/audio/39d23e5d-b238-46cd-bebd-1837825d938e.m3u8",
        "audio_128kb": "https://kukufm.akamaized.net/audio/39d23e5d-b238-46cd-bebd-1837825d938e128kb.m3u8",
        "audio_64kb": "https://kukufm.akamaized.net/audio/39d23e5d-b238-46cd-bebd-1837825d938e64kb.m3u8",
        "audio_24kb": "https://kukufm.akamaized.net/audio/39d23e5d-b238-46cd-bebd-1837825d938e24kb.m3u8"
      },
      "dynamic_link": "https://applinks.kukufm.com/nQtzx5zqkpTDhvtk6",
      "is_premium": true,
      "is_play_locked": false,
      "is_locked": true,
      "is_fictional": false,
      "index": 13,
      "show_id": 201794,
      "season_no": 1,
      "is_demo_premium": false,
      "is_free_unlocked": true,
      "media_size": 16936027,
      "published_on": "2023-08-04T05:18:15.594728+00:00",
      "thumbnail_image": "https://images.cdn.kukufm.com/w:200/f:jpg/q:85/https://s3.ap-south-1.amazonaws.com/kukufm/channel_icons/079c93f521434619a89b7d525b9643c7.png",
      "web_uri": "/episode/vishnupuranam-ep-12",
      "view_type": "default",
      "unlocking_nudge_text": "",
      "unlocking_nudge_text_v2": "",
      "has_srt": false,
      "has_liked": false,
      "seek_position": 0,
      "can_download": true,
      "is_downloaded": false,
      "is_self": false,
      "unlock_type": "subscription",
      "transcript": {}
    },
    {
      "id": 671142,
      "title": "13. Yemanin kadhai",
      "slug": "vishnupuranam-ep-13",
      "status": "live",
      "image": "https://images.cdn.kukufm.com/f:webp/https://s3.ap-south-1.amazonaws.com/kukufm/channel_icons/079c93f521434619a89b7d525b9643c7.png",
      "original_image": "https://s3.ap-south-1.amazonaws.com/kukufm/channel_icons/079c93f521434619a89b7d525b9643c7.png",
      "duration_s": 1301,
      "image_sizes": {
        "100": "https://images.cdn.kukufm.com/w:100/f:webp/q:85/https://s3.ap-south-1.amazonaws.com/kukufm/channel_icons/079c93f521434619a89b7d525b9643c7.png",
        "150": "https://images.cdn.kukufm.com/w:150/f:webp/q:85/https://s3.ap-south-1.amazonaws.com/kukufm/channel_icons/079c93f521434619a89b7d525b9643c7.png",
        "200": "https://images.cdn.kukufm.com/w:200/f:webp/q:85/https://s3.ap-south-1.amazonaws.com/kukufm/channel_icons/079c93f521434619a89b7d525b9643c7.png",
        "300": "https://images.cdn.kukufm.com/w:300/f:webp/q:85/https://s3.ap-south-1.amazonaws.com/kukufm/channel_icons/079c93f521434619a89b7d525b9643c7.png"
      },
      "n_likes": 0,
      "n_shares": 0,
      "n_plays": null,
      "n_listens": 2380,
      "n_comments": 0,
      "cover_type": null,
      "content": {
        "converted_hls_url": "https://kukufm.akamaized.net/audio/f5b982de-0917-4ea6-914d-aeeb9f48f8ee.m3u8",
        "audio_128kb": "https://kukufm.akamaized.net/audio/f5b982de-0917-4ea6-914d-aeeb9f48f8ee128kb.m3u8",
        "audio_64kb": "https://kukufm.akamaized.net/audio/f5b982de-0917-4ea6-914d-aeeb9f48f8ee64kb.m3u8",
        "audio_24kb": "https://kukufm.akamaized.net/audio/f5b982de-0917-4ea6-914d-aeeb9f48f8ee24kb.m3u8"
      },
      "dynamic_link": "https://applinks.kukufm.com/JX7RY3Qj2q3UzmSh8",
      "is_premium": true,
      "is_play_locked": false,
      "is_locked": true,
      "is_fictional": false,
      "index": 14,
      "show_id": 201794,
      "season_no": 1,
      "is_demo_premium": false,
      "is_free_unlocked": true,
      "media_size": 27029668,
      "published_on": "2023-08-04T05:18:15.594728+00:00",
      "thumbnail_image": "https://images.cdn.kukufm.com/w:200/f:jpg/q:85/https://s3.ap-south-1.amazonaws.com/kukufm/channel_icons/079c93f521434619a89b7d525b9643c7.png",
      "web_uri": "/episode/vishnupuranam-ep-13",
      "view_type": "default",
      "unlocking_nudge_text": "",
      "unlocking_nudge_text_v2": "",
      "has_srt": false,
      "has_liked": false,
      "seek_position": 0,
      "can_download": true,
      "is_downloaded": false,
      "is_self": false,
      "unlock_type": "subscription",
      "transcript": {}
    },
    {
      "id": 671143,
      "title": "14. 7'aavadhu manu",
      "slug": "vishnupuranam-ep-14",
      "status": "live",
      "image": "https://images.cdn.kukufm.com/f:webp/https://s3.ap-south-1.amazonaws.com/kukufm/channel_icons/079c93f521434619a89b7d525b9643c7.png",
      "original_image": "https://s3.ap-south-1.amazonaws.com/kukufm/channel_icons/079c93f521434619a89b7d525b9643c7.png",
      "duration_s": 614,
      "image_sizes": {
        "100": "https://images.cdn.kukufm.com/w:100/f:webp/q:85/https://s3.ap-south-1.amazonaws.com/kukufm/channel_icons/079c93f521434619a89b7d525b9643c7.png",
        "150": "https://images.cdn.kukufm.com/w:150/f:webp/q:85/https://s3.ap-south-1.amazonaws.com/kukufm/channel_icons/079c93f521434619a89b7d525b9643c7.png",
        "200": "https://images.cdn.kukufm.com/w:200/f:webp/q:85/https://s3.ap-south-1.amazonaws.com/kukufm/channel_icons/079c93f521434619a89b7d525b9643c7.png",
        "300": "https://images.cdn.kukufm.com/w:300/f:webp/q:85/https://s3.ap-south-1.amazonaws.com/kukufm/channel_icons/079c93f521434619a89b7d525b9643c7.png"
      },
      "n_likes": 0,
      "n_shares": 0,
      "n_plays": null,
      "n_listens": 1777,
      "n_comments": 1,
      "cover_type": null,
      "content": {
        "converted_hls_url": "https://kukufm.akamaized.net/audio/3917a3bb-0fcc-46c9-a819-ef7adc706b61.m3u8",
        "audio_128kb": "https://kukufm.akamaized.net/audio/3917a3bb-0fcc-46c9-a819-ef7adc706b61128kb.m3u8",
        "audio_64kb": "https://kukufm.akamaized.net/audio/3917a3bb-0fcc-46c9-a819-ef7adc706b6164kb.m3u8",
        "audio_24kb": "https://kukufm.akamaized.net/audio/3917a3bb-0fcc-46c9-a819-ef7adc706b6124kb.m3u8"
      },
      "dynamic_link": "https://applinks.kukufm.com/ScjkmGGjbZajxj6dA",
      "is_premium": true,
      "is_play_locked": false,
      "is_locked": true,
      "is_fictional": false,
      "index": 15,
      "show_id": 201794,
      "season_no": 1,
      "is_demo_premium": false,
      "is_free_unlocked": true,
      "media_size": 13110357,
      "published_on": "2023-08-04T05:18:15.594728+00:00",
      "thumbnail_image": "https://images.cdn.kukufm.com/w:200/f:jpg/q:85/https://s3.ap-south-1.amazonaws.com/kukufm/channel_icons/079c93f521434619a89b7d525b9643c7.png",
      "web_uri": "/episode/vishnupuranam-ep-14",
      "view_type": "default",
      "unlocking_nudge_text": "",
      "unlocking_nudge_text_v2": "",
      "has_srt": false,
      "has_liked": false,
      "seek_position": 0,
      "can_download": true,
      "is_downloaded": false,
      "is_self": false,
      "unlock_type": "subscription",
      "transcript": {}
    },
    {
      "id": 671144,
      "title": "15. Isabagu",
      "slug": "vishnupuranam-ep-15",
      "status": "live",
      "image": "https://images.cdn.kukufm.com/f:webp/https://s3.ap-south-1.amazonaws.com/kukufm/channel_icons/079c93f521434619a89b7d525b9643c7.png",
      "original_image": "https://s3.ap-south-1.amazonaws.com/kukufm/channel_icons/079c93f521434619a89b7d525b9643c7.png",
      "duration_s": 813,
      "image_sizes": {
        "100": "https://images.cdn.kukufm.com/w:100/f:webp/q:85/https://s3.ap-south-1.amazonaws.com/kukufm/channel_icons/079c93f521434619a89b7d525b9643c7.png",
        "150": "https://images.cdn.kukufm.com/w:150/f:webp/q:85/https://s3.ap-south-1.amazonaws.com/kukufm/channel_icons/079c93f521434619a89b7d525b9643c7.png",
        "200": "https://images.cdn.kukufm.com/w:200/f:webp/q:85/https://s3.ap-south-1.amazonaws.com/kukufm/channel_icons/079c93f521434619a89b7d525b9643c7.png",
        "300": "https://images.cdn.kukufm.com/w:300/f:webp/q:85/https://s3.ap-south-1.amazonaws.com/kukufm/channel_icons/079c93f521434619a89b7d525b9643c7.png"
      },
      "n_likes": 0,
      "n_shares": 0,
      "n_plays": null,
      "n_listens": 1716,
      "n_comments": 0,
      "cover_type": null,
      "content": {
        "converted_hls_url": "https://kukufm.akamaized.net/audio/63dd3d88-7734-484c-8107-eafc74dcb169.m3u8",
        "audio_128kb": "https://kukufm.akamaized.net/audio/63dd3d88-7734-484c-8107-eafc74dcb169128kb.m3u8",
        "audio_64kb": "https://kukufm.akamaized.net/audio/63dd3d88-7734-484c-8107-eafc74dcb16964kb.m3u8",
        "audio_24kb": "https://kukufm.akamaized.net/audio/63dd3d88-7734-484c-8107-eafc74dcb16924kb.m3u8"
      },
      "dynamic_link": "https://applinks.kukufm.com/D6c3LEGiU8n5XxeBA",
      "is_premium": true,
      "is_play_locked": false,
      "is_locked": true,
      "is_fictional": false,
      "index": 16,
      "show_id": 201794,
      "season_no": 1,
      "is_demo_premium": false,
      "is_free_unlocked": true,
      "media_size": 16949340,
      "published_on": "2023-08-04T05:18:15.594728+00:00",
      "thumbnail_image": "https://images.cdn.kukufm.com/w:200/f:jpg/q:85/https://s3.ap-south-1.amazonaws.com/kukufm/channel_icons/079c93f521434619a89b7d525b9643c7.png",
      "web_uri": "/episode/vishnupuranam-ep-15",
      "view_type": "default",
      "unlocking_nudge_text": "",
      "unlocking_nudge_text_v2": "",
      "has_srt": false,
      "has_liked": false,
      "seek_position": 0,
      "can_download": true,
      "is_downloaded": false,
      "is_self": false,
      "unlock_type": "subscription",
      "transcript": {}
    },
    {
      "id": 671145,
      "title": "16. Seethai mudhal",
      "slug": "vishnupuranam-ep-16",
      "status": "live",
      "image": "https://images.cdn.kukufm.com/f:webp/https://s3.ap-south-1.amazonaws.com/kukufm/channel_icons/079c93f521434619a89b7d525b9643c7.png",
      "original_image": "https://s3.ap-south-1.amazonaws.com/kukufm/channel_icons/079c93f521434619a89b7d525b9643c7.png",
      "duration_s": 505,
      "image_sizes": {
        "100": "https://images.cdn.kukufm.com/w:100/f:webp/q:85/https://s3.ap-south-1.amazonaws.com/kukufm/channel_icons/079c93f521434619a89b7d525b9643c7.png",
        "150": "https://images.cdn.kukufm.com/w:150/f:webp/q:85/https://s3.ap-south-1.amazonaws.com/kukufm/channel_icons/079c93f521434619a89b7d525b9643c7.png",
        "200": "https://images.cdn.kukufm.com/w:200/f:webp/q:85/https://s3.ap-south-1.amazonaws.com/kukufm/channel_icons/079c93f521434619a89b7d525b9643c7.png",
        "300": "https://images.cdn.kukufm.com/w:300/f:webp/q:85/https://s3.ap-south-1.amazonaws.com/kukufm/channel_icons/079c93f521434619a89b7d525b9643c7.png"
      },
      "n_likes": 0,
      "n_shares": 0,
      "n_plays": null,
      "n_listens": 1627,
      "n_comments": 0,
      "cover_type": null,
      "content": {
        "converted_hls_url": "https://kukufm.akamaized.net/audio/0c2ee642-fa77-4875-a6ba-3ef930fb22f9.m3u8",
        "audio_128kb": "https://kukufm.akamaized.net/audio/0c2ee642-fa77-4875-a6ba-3ef930fb22f9128kb.m3u8",
        "audio_64kb": "https://kukufm.akamaized.net/audio/0c2ee642-fa77-4875-a6ba-3ef930fb22f964kb.m3u8",
        "audio_24kb": "https://kukufm.akamaized.net/audio/0c2ee642-fa77-4875-a6ba-3ef930fb22f924kb.m3u8"
      },
      "dynamic_link": "https://applinks.kukufm.com/mExrsV3BQ9gi7Z8X9",
      "is_premium": true,
      "is_play_locked": false,
      "is_locked": true,
      "is_fictional": false,
      "index": 17,
      "show_id": 201794,
      "season_no": 1,
      "is_demo_premium": false,
      "is_free_unlocked": true,
      "media_size": 10613607,
      "published_on": "2023-08-04T05:18:15.594728+00:00",
      "thumbnail_image": "https://images.cdn.kukufm.com/w:200/f:jpg/q:85/https://s3.ap-south-1.amazonaws.com/kukufm/channel_icons/079c93f521434619a89b7d525b9643c7.png",
      "web_uri": "/episode/vishnupuranam-ep-16",
      "view_type": "default",
      "unlocking_nudge_text": "",
      "unlocking_nudge_text_v2": "",
      "has_srt": false,
      "has_liked": false,
      "seek_position": 0,
      "can_download": true,
      "is_downloaded": false,
      "is_self": false,
      "unlock_type": "subscription",
      "transcript": {}
    },
    {
      "id": 671146,
      "title": "17. Parasuramar",
      "slug": "vishnupuranam-ep-17",
      "status": "live",
      "image": "https://images.cdn.kukufm.com/f:webp/https://s3.ap-south-1.amazonaws.com/kukufm/channel_icons/079c93f521434619a89b7d525b9643c7.png",
      "original_image": "https://s3.ap-south-1.amazonaws.com/kukufm/channel_icons/079c93f521434619a89b7d525b9643c7.png",
      "duration_s": 599,
      "image_sizes": {
        "100": "https://images.cdn.kukufm.com/w:100/f:webp/q:85/https://s3.ap-south-1.amazonaws.com/kukufm/channel_icons/079c93f521434619a89b7d525b9643c7.png",
        "150": "https://images.cdn.kukufm.com/w:150/f:webp/q:85/https://s3.ap-south-1.amazonaws.com/kukufm/channel_icons/079c93f521434619a89b7d525b9643c7.png",
        "200": "https://images.cdn.kukufm.com/w:200/f:webp/q:85/https://s3.ap-south-1.amazonaws.com/kukufm/channel_icons/079c93f521434619a89b7d525b9643c7.png",
        "300": "https://images.cdn.kukufm.com/w:300/f:webp/q:85/https://s3.ap-south-1.amazonaws.com/kukufm/channel_icons/079c93f521434619a89b7d525b9643c7.png"
      },
      "n_likes": 0,
      "n_shares": 0,
      "n_plays": null,
      "n_listens": 1545,
      "n_comments": 0,
      "cover_type": null,
      "content": {
        "converted_hls_url": "https://kukufm.akamaized.net/audio/f2273925-6f43-49d6-bfe1-71e5b40cd36e.m3u8",
        "audio_128kb": "https://kukufm.akamaized.net/audio/f2273925-6f43-49d6-bfe1-71e5b40cd36e128kb.m3u8",
        "audio_64kb": "https://kukufm.akamaized.net/audio/f2273925-6f43-49d6-bfe1-71e5b40cd36e64kb.m3u8",
        "audio_24kb": "https://kukufm.akamaized.net/audio/f2273925-6f43-49d6-bfe1-71e5b40cd36e24kb.m3u8"
      },
      "dynamic_link": "https://applinks.kukufm.com/A3RrNVHHNxDNFfQY9",
      "is_premium": true,
      "is_play_locked": false,
      "is_locked": true,
      "is_fictional": false,
      "index": 18,
      "show_id": 201794,
      "season_no": 1,
      "is_demo_premium": false,
      "is_free_unlocked": true,
      "media_size": 12554297,
      "published_on": "2023-08-04T05:18:15.594728+00:00",
      "thumbnail_image": "https://images.cdn.kukufm.com/w:200/f:jpg/q:85/https://s3.ap-south-1.amazonaws.com/kukufm/channel_icons/079c93f521434619a89b7d525b9643c7.png",
      "web_uri": "/episode/vishnupuranam-ep-17",
      "view_type": "default",
      "unlocking_nudge_text": "",
      "unlocking_nudge_text_v2": "",
      "has_srt": false,
      "has_liked": false,
      "seek_position": 0,
      "can_download": true,
      "is_downloaded": false,
      "is_self": false,
      "unlock_type": "subscription",
      "transcript": {}
    },
    {
      "id": 671147,
      "title": "18. Guruvin vamsam",
      "slug": "vishnupuranam-ep-18",
      "status": "live",
      "image": "https://images.cdn.kukufm.com/f:webp/https://s3.ap-south-1.amazonaws.com/kukufm/channel_icons/079c93f521434619a89b7d525b9643c7.png",
      "original_image": "https://s3.ap-south-1.amazonaws.com/kukufm/channel_icons/079c93f521434619a89b7d525b9643c7.png",
      "duration_s": 511,
      "image_sizes": {
        "100": "https://images.cdn.kukufm.com/w:100/f:webp/q:85/https://s3.ap-south-1.amazonaws.com/kukufm/channel_icons/079c93f521434619a89b7d525b9643c7.png",
        "150": "https://images.cdn.kukufm.com/w:150/f:webp/q:85/https://s3.ap-south-1.amazonaws.com/kukufm/channel_icons/079c93f521434619a89b7d525b9643c7.png",
        "200": "https://images.cdn.kukufm.com/w:200/f:webp/q:85/https://s3.ap-south-1.amazonaws.com/kukufm/channel_icons/079c93f521434619a89b7d525b9643c7.png",
        "300": "https://images.cdn.kukufm.com/w:300/f:webp/q:85/https://s3.ap-south-1.amazonaws.com/kukufm/channel_icons/079c93f521434619a89b7d525b9643c7.png"
      },
      "n_likes": 0,
      "n_shares": 0,
      "n_plays": null,
      "n_listens": 1440,
      "n_comments": 0,
      "cover_type": null,
      "content": {
        "converted_hls_url": "https://kukufm.akamaized.net/audio/0023b5ec-6b16-4958-b548-36edf2898c65.m3u8",
        "audio_128kb": "https://kukufm.akamaized.net/audio/0023b5ec-6b16-4958-b548-36edf2898c65128kb.m3u8",
        "audio_64kb": "https://kukufm.akamaized.net/audio/0023b5ec-6b16-4958-b548-36edf2898c6564kb.m3u8",
        "audio_24kb": "https://kukufm.akamaized.net/audio/0023b5ec-6b16-4958-b548-36edf2898c6524kb.m3u8"
      },
      "dynamic_link": "https://applinks.kukufm.com/BtxqBtBx53H8bCr16",
      "is_premium": true,
      "is_play_locked": false,
      "is_locked": true,
      "is_fictional": false,
      "index": 19,
      "show_id": 201794,
      "season_no": 1,
      "is_demo_premium": false,
      "is_free_unlocked": true,
      "media_size": 10722261,
      "published_on": "2023-08-04T05:18:15.594728+00:00",
      "thumbnail_image": "https://images.cdn.kukufm.com/w:200/f:jpg/q:85/https://s3.ap-south-1.amazonaws.com/kukufm/channel_icons/079c93f521434619a89b7d525b9643c7.png",
      "web_uri": "/episode/vishnupuranam-ep-18",
      "view_type": "default",
      "unlocking_nudge_text": "",
      "unlocking_nudge_text_v2": "",
      "has_srt": false,
      "has_liked": false,
      "seek_position": 0,
      "can_download": true,
      "is_downloaded": false,
      "is_self": false,
      "unlock_type": "subscription",
      "transcript": {}
    },
    {
      "id": 671148,
      "title": "19. Guruvamsa kadhai",
      "slug": "vishnupuranam-ep-19",
      "status": "live",
      "image": "https://images.cdn.kukufm.com/f:webp/https://s3.ap-south-1.amazonaws.com/kukufm/channel_icons/079c93f521434619a89b7d525b9643c7.png",
      "original_image": "https://s3.ap-south-1.amazonaws.com/kukufm/channel_icons/079c93f521434619a89b7d525b9643c7.png",
      "duration_s": 397,
      "image_sizes": {
        "100": "https://images.cdn.kukufm.com/w:100/f:webp/q:85/https://s3.ap-south-1.amazonaws.com/kukufm/channel_icons/079c93f521434619a89b7d525b9643c7.png",
        "150": "https://images.cdn.kukufm.com/w:150/f:webp/q:85/https://s3.ap-south-1.amazonaws.com/kukufm/channel_icons/079c93f521434619a89b7d525b9643c7.png",
        "200": "https://images.cdn.kukufm.com/w:200/f:webp/q:85/https://s3.ap-south-1.amazonaws.com/kukufm/channel_icons/079c93f521434619a89b7d525b9643c7.png",
        "300": "https://images.cdn.kukufm.com/w:300/f:webp/q:85/https://s3.ap-south-1.amazonaws.com/kukufm/channel_icons/079c93f521434619a89b7d525b9643c7.png"
      },
      "n_likes": 0,
      "n_shares": 0,
      "n_plays": null,
      "n_listens": 1325,
      "n_comments": 0,
      "cover_type": null,
      "content": {
        "converted_hls_url": "https://kukufm.akamaized.net/audio/58cb5bbb-3306-499e-8279-beebad62e2cd.m3u8",
        "audio_128kb": "https://kukufm.akamaized.net/audio/58cb5bbb-3306-499e-8279-beebad62e2cd128kb.m3u8",
        "audio_64kb": "https://kukufm.akamaized.net/audio/58cb5bbb-3306-499e-8279-beebad62e2cd64kb.m3u8",
        "audio_24kb": "https://kukufm.akamaized.net/audio/58cb5bbb-3306-499e-8279-beebad62e2cd24kb.m3u8"
      },
      "dynamic_link": "https://applinks.kukufm.com/tgTHHh7qfZ3wrV627",
      "is_premium": true,
      "is_play_locked": false,
      "is_locked": true,
      "is_fictional": false,
      "index": 20,
      "show_id": 201794,
      "season_no": 1,
      "is_demo_premium": false,
      "is_free_unlocked": true,
      "media_size": 8604397,
      "published_on": "2023-08-04T05:18:15.594728+00:00",
      "thumbnail_image": "https://images.cdn.kukufm.com/w:200/f:jpg/q:85/https://s3.ap-south-1.amazonaws.com/kukufm/channel_icons/079c93f521434619a89b7d525b9643c7.png",
      "web_uri": "/episode/vishnupuranam-ep-19",
      "view_type": "default",
      "unlocking_nudge_text": "",
      "unlocking_nudge_text_v2": "",
      "has_srt": false,
      "has_liked": false,
      "seek_position": 0,
      "can_download": true,
      "is_downloaded": false,
      "is_self": false,
      "unlock_type": "subscription",
      "transcript": {}
    },
    {
      "id": 671149,
      "title": "20. Krishnarin avathara ragasiyam",
      "slug": "vishnupuranam-ep-20",
      "status": "live",
      "image": "https://images.cdn.kukufm.com/f:webp/https://s3.ap-south-1.amazonaws.com/kukufm/channel_icons/079c93f521434619a89b7d525b9643c7.png",
      "original_image": "https://s3.ap-south-1.amazonaws.com/kukufm/channel_icons/079c93f521434619a89b7d525b9643c7.png",
      "duration_s": 641,
      "image_sizes": {
        "100": "https://images.cdn.kukufm.com/w:100/f:webp/q:85/https://s3.ap-south-1.amazonaws.com/kukufm/channel_icons/079c93f521434619a89b7d525b9643c7.png",
        "150": "https://images.cdn.kukufm.com/w:150/f:webp/q:85/https://s3.ap-south-1.amazonaws.com/kukufm/channel_icons/079c93f521434619a89b7d525b9643c7.png",
        "200": "https://images.cdn.kukufm.com/w:200/f:webp/q:85/https://s3.ap-south-1.amazonaws.com/kukufm/channel_icons/079c93f521434619a89b7d525b9643c7.png",
        "300": "https://images.cdn.kukufm.com/w:300/f:webp/q:85/https://s3.ap-south-1.amazonaws.com/kukufm/channel_icons/079c93f521434619a89b7d525b9643c7.png"
      },
      "n_likes": 0,
      "n_shares": 0,
      "n_plays": null,
      "n_listens": 1433,
      "n_comments": 0,
      "cover_type": null,
      "content": {
        "converted_hls_url": "https://kukufm.akamaized.net/audio/df750e55-41fd-4c0e-9c69-0bb681470b88.m3u8",
        "audio_128kb": "https://kukufm.akamaized.net/audio/df750e55-41fd-4c0e-9c69-0bb681470b88128kb.m3u8",
        "audio_64kb": "https://kukufm.akamaized.net/audio/df750e55-41fd-4c0e-9c69-0bb681470b8864kb.m3u8",
        "audio_24kb": "https://kukufm.akamaized.net/audio/df750e55-41fd-4c0e-9c69-0bb681470b8824kb.m3u8"
      },
      "dynamic_link": "https://applinks.kukufm.com/6sszGmHBAz4rz5cx7",
      "is_premium": true,
      "is_play_locked": false,
      "is_locked": true,
      "is_fictional": false,
      "index": 21,
      "show_id": 201794,
      "season_no": 1,
      "is_demo_premium": false,
      "is_free_unlocked": true,
      "media_size": 13359557,
      "published_on": "2023-08-04T05:18:15.594728+00:00",
      "thumbnail_image": "https://images.cdn.kukufm.com/w:200/f:jpg/q:85/https://s3.ap-south-1.amazonaws.com/kukufm/channel_icons/079c93f521434619a89b7d525b9643c7.png",
      "web_uri": "/episode/vishnupuranam-ep-20",
      "view_type": "default",
      "unlocking_nudge_text": "",
      "unlocking_nudge_text_v2": "",
      "has_srt": false,
      "has_liked": false,
      "seek_position": 0,
      "can_download": true,
      "is_downloaded": false,
      "is_self": false,
      "unlock_type": "subscription",
      "transcript": {}
    },
    {
      "id": 671150,
      "title": "21. Krishnar'in Pirappu",
      "slug": "vishnupuranam-ep-21",
      "status": "live",
      "image": "https://images.cdn.kukufm.com/f:webp/https://s3.ap-south-1.amazonaws.com/kukufm/channel_icons/079c93f521434619a89b7d525b9643c7.png",
      "original_image": "https://s3.ap-south-1.amazonaws.com/kukufm/channel_icons/079c93f521434619a89b7d525b9643c7.png",
      "duration_s": 815,
      "image_sizes": {
        "100": "https://images.cdn.kukufm.com/w:100/f:webp/q:85/https://s3.ap-south-1.amazonaws.com/kukufm/channel_icons/079c93f521434619a89b7d525b9643c7.png",
        "150": "https://images.cdn.kukufm.com/w:150/f:webp/q:85/https://s3.ap-south-1.amazonaws.com/kukufm/channel_icons/079c93f521434619a89b7d525b9643c7.png",
        "200": "https://images.cdn.kukufm.com/w:200/f:webp/q:85/https://s3.ap-south-1.amazonaws.com/kukufm/channel_icons/079c93f521434619a89b7d525b9643c7.png",
        "300": "https://images.cdn.kukufm.com/w:300/f:webp/q:85/https://s3.ap-south-1.amazonaws.com/kukufm/channel_icons/079c93f521434619a89b7d525b9643c7.png"
      },
      "n_likes": 0,
      "n_shares": 0,
      "n_plays": null,
      "n_listens": 1477,
      "n_comments": 0,
      "cover_type": null,
      "content": {
        "converted_hls_url": "https://kukufm.akamaized.net/audio/26adf0b5-0b18-48d6-8c77-9013ed0c6241.m3u8",
        "audio_128kb": "https://kukufm.akamaized.net/audio/26adf0b5-0b18-48d6-8c77-9013ed0c6241128kb.m3u8",
        "audio_64kb": "https://kukufm.akamaized.net/audio/26adf0b5-0b18-48d6-8c77-9013ed0c624164kb.m3u8",
        "audio_24kb": "https://kukufm.akamaized.net/audio/26adf0b5-0b18-48d6-8c77-9013ed0c624124kb.m3u8"
      },
      "dynamic_link": "https://applinks.kukufm.com/xWPLtJNZM8dWureWA",
      "is_premium": true,
      "is_play_locked": false,
      "is_locked": true,
      "is_fictional": false,
      "index": 22,
      "show_id": 201794,
      "season_no": 1,
      "is_demo_premium": false,
      "is_free_unlocked": true,
      "media_size": 16913963,
      "published_on": "2023-08-04T05:18:15.594728+00:00",
      "thumbnail_image": "https://images.cdn.kukufm.com/w:200/f:jpg/q:85/https://s3.ap-south-1.amazonaws.com/kukufm/channel_icons/079c93f521434619a89b7d525b9643c7.png",
      "web_uri": "/episode/vishnupuranam-ep-21",
      "view_type": "default",
      "unlocking_nudge_text": "",
      "unlocking_nudge_text_v2": "",
      "has_srt": false,
      "has_liked": false,
      "seek_position": 0,
      "can_download": true,
      "is_downloaded": false,
      "is_self": false,
      "unlock_type": "subscription",
      "transcript": {}
    },
    {
      "id": 671151,
      "title": "22. Vasu maindhan",
      "slug": "vishnupuranam-ep-22",
      "status": "live",
      "image": "https://images.cdn.kukufm.com/f:webp/https://s3.ap-south-1.amazonaws.com/kukufm/channel_icons/079c93f521434619a89b7d525b9643c7.png",
      "original_image": "https://s3.ap-south-1.amazonaws.com/kukufm/channel_icons/079c93f521434619a89b7d525b9643c7.png",
      "duration_s": 892,
      "image_sizes": {
        "100": "https://images.cdn.kukufm.com/w:100/f:webp/q:85/https://s3.ap-south-1.amazonaws.com/kukufm/channel_icons/079c93f521434619a89b7d525b9643c7.png",
        "150": "https://images.cdn.kukufm.com/w:150/f:webp/q:85/https://s3.ap-south-1.amazonaws.com/kukufm/channel_icons/079c93f521434619a89b7d525b9643c7.png",
        "200": "https://images.cdn.kukufm.com/w:200/f:webp/q:85/https://s3.ap-south-1.amazonaws.com/kukufm/channel_icons/079c93f521434619a89b7d525b9643c7.png",
        "300": "https://images.cdn.kukufm.com/w:300/f:webp/q:85/https://s3.ap-south-1.amazonaws.com/kukufm/channel_icons/079c93f521434619a89b7d525b9643c7.png"
      },
      "n_likes": 0,
      "n_shares": 0,
      "n_plays": null,
      "n_listens": 1326,
      "n_comments": 0,
      "cover_type": null,
      "content": {
        "converted_hls_url": "https://kukufm.akamaized.net/audio/af8b8a59-6ebf-4201-9008-03c47e5d07e0.m3u8",
        "audio_128kb": "https://kukufm.akamaized.net/audio/af8b8a59-6ebf-4201-9008-03c47e5d07e0128kb.m3u8",
        "audio_64kb": "https://kukufm.akamaized.net/audio/af8b8a59-6ebf-4201-9008-03c47e5d07e064kb.m3u8",
        "audio_24kb": "https://kukufm.akamaized.net/audio/af8b8a59-6ebf-4201-9008-03c47e5d07e024kb.m3u8"
      },
      "dynamic_link": "https://applinks.kukufm.com/oddaowPpzNtF2JQn7",
      "is_premium": true,
      "is_play_locked": false,
      "is_locked": true,
      "is_fictional": false,
      "index": 23,
      "show_id": 201794,
      "season_no": 1,
      "is_demo_premium": false,
      "is_free_unlocked": true,
      "media_size": 19104590,
      "published_on": "2023-08-04T05:18:15.594728+00:00",
      "thumbnail_image": "https://images.cdn.kukufm.com/w:200/f:jpg/q:85/https://s3.ap-south-1.amazonaws.com/kukufm/channel_icons/079c93f521434619a89b7d525b9643c7.png",
      "web_uri": "/episode/vishnupuranam-ep-22",
      "view_type": "default",
      "unlocking_nudge_text": "",
      "unlocking_nudge_text_v2": "",
      "has_srt": false,
      "has_liked": false,
      "seek_position": 0,
      "can_download": true,
      "is_downloaded": false,
      "is_self": false,
      "unlock_type": "subscription",
      "transcript": {}
    },
    {
      "id": 671152,
      "title": "23. Agasuran",
      "slug": "vishnupuranam-ep-23",
      "status": "live",
      "image": "https://images.cdn.kukufm.com/f:webp/https://s3.ap-south-1.amazonaws.com/kukufm/channel_icons/079c93f521434619a89b7d525b9643c7.png",
      "original_image": "https://s3.ap-south-1.amazonaws.com/kukufm/channel_icons/079c93f521434619a89b7d525b9643c7.png",
      "duration_s": 904,
      "image_sizes": {
        "100": "https://images.cdn.kukufm.com/w:100/f:webp/q:85/https://s3.ap-south-1.amazonaws.com/kukufm/channel_icons/079c93f521434619a89b7d525b9643c7.png",
        "150": "https://images.cdn.kukufm.com/w:150/f:webp/q:85/https://s3.ap-south-1.amazonaws.com/kukufm/channel_icons/079c93f521434619a89b7d525b9643c7.png",
        "200": "https://images.cdn.kukufm.com/w:200/f:webp/q:85/https://s3.ap-south-1.amazonaws.com/kukufm/channel_icons/079c93f521434619a89b7d525b9643c7.png",
        "300": "https://images.cdn.kukufm.com/w:300/f:webp/q:85/https://s3.ap-south-1.amazonaws.com/kukufm/channel_icons/079c93f521434619a89b7d525b9643c7.png"
      },
      "n_likes": 0,
      "n_shares": 0,
      "n_plays": null,
      "n_listens": 2294,
      "n_comments": 0,
      "cover_type": null,
      "content": {
        "converted_hls_url": "https://kukufm.akamaized.net/audio/ee1e36d4-fe83-4c4a-a54d-8d8a5011683a.m3u8",
        "audio_128kb": "https://kukufm.akamaized.net/audio/ee1e36d4-fe83-4c4a-a54d-8d8a5011683a128kb.m3u8",
        "audio_64kb": "https://kukufm.akamaized.net/audio/ee1e36d4-fe83-4c4a-a54d-8d8a5011683a64kb.m3u8",
        "audio_24kb": "https://kukufm.akamaized.net/audio/ee1e36d4-fe83-4c4a-a54d-8d8a5011683a24kb.m3u8"
      },
      "dynamic_link": "https://applinks.kukufm.com/twn8vTXssuQowR5H8",
      "is_premium": true,
      "is_play_locked": false,
      "is_locked": true,
      "is_fictional": false,
      "index": 24,
      "show_id": 201794,
      "season_no": 1,
      "is_demo_premium": false,
      "is_free_unlocked": true,
      "media_size": 18690461,
      "published_on": "2023-08-04T05:18:15.594728+00:00",
      "thumbnail_image": "https://images.cdn.kukufm.com/w:200/f:jpg/q:85/https://s3.ap-south-1.amazonaws.com/kukufm/channel_icons/079c93f521434619a89b7d525b9643c7.png",
      "web_uri": "/episode/vishnupuranam-ep-23",
      "view_type": "default",
      "unlocking_nudge_text": "",
      "unlocking_nudge_text_v2": "",
      "has_srt": false,
      "has_liked": false,
      "seek_position": 0,
      "can_download": true,
      "is_downloaded": false,
      "is_self": false,
      "unlock_type": "subscription",
      "transcript": {}
    },
    {
      "id": 671153,
      "title": "24. Kamsanin vatham - conclusion",
      "slug": "vishnupuranam-ep-24",
      "status": "live",
      "image": "https://images.cdn.kukufm.com/f:webp/https://s3.ap-south-1.amazonaws.com/kukufm/channel_icons/079c93f521434619a89b7d525b9643c7.png",
      "original_image": "https://s3.ap-south-1.amazonaws.com/kukufm/channel_icons/079c93f521434619a89b7d525b9643c7.png",
      "duration_s": 770,
      "image_sizes": {
        "100": "https://images.cdn.kukufm.com/w:100/f:webp/q:85/https://s3.ap-south-1.amazonaws.com/kukufm/channel_icons/079c93f521434619a89b7d525b9643c7.png",
        "150": "https://images.cdn.kukufm.com/w:150/f:webp/q:85/https://s3.ap-south-1.amazonaws.com/kukufm/channel_icons/079c93f521434619a89b7d525b9643c7.png",
        "200": "https://images.cdn.kukufm.com/w:200/f:webp/q:85/https://s3.ap-south-1.amazonaws.com/kukufm/channel_icons/079c93f521434619a89b7d525b9643c7.png",
        "300": "https://images.cdn.kukufm.com/w:300/f:webp/q:85/https://s3.ap-south-1.amazonaws.com/kukufm/channel_icons/079c93f521434619a89b7d525b9643c7.png"
      },
      "n_likes": 0,
      "n_shares": 0,
      "n_plays": null,
      "n_listens": 1202,
      "n_comments": 0,
      "cover_type": null,
      "content": {
        "converted_hls_url": "https://kukufm.akamaized.net/audio/cbe7f751-c551-4d30-a378-5a73959a25aa.m3u8",
        "audio_128kb": "https://kukufm.akamaized.net/audio/cbe7f751-c551-4d30-a378-5a73959a25aa128kb.m3u8",
        "audio_64kb": "https://kukufm.akamaized.net/audio/cbe7f751-c551-4d30-a378-5a73959a25aa64kb.m3u8",
        "audio_24kb": "https://kukufm.akamaized.net/audio/cbe7f751-c551-4d30-a378-5a73959a25aa24kb.m3u8"
      },
      "dynamic_link": "https://applinks.kukufm.com/QHNWqhnaMEtHLAVA8",
      "is_premium": true,
      "is_play_locked": false,
      "is_locked": true,
      "is_fictional": false,
      "index": 25,
      "show_id": 201794,
      "season_no": 1,
      "is_demo_premium": false,
      "is_free_unlocked": true,
      "media_size": 16044575,
      "published_on": "2023-08-04T05:18:15.594728+00:00",
      "thumbnail_image": "https://images.cdn.kukufm.com/w:200/f:jpg/q:85/https://s3.ap-south-1.amazonaws.com/kukufm/channel_icons/079c93f521434619a89b7d525b9643c7.png",
      "web_uri": "/episode/vishnupuranam-ep-24",
      "view_type": "default",
      "unlocking_nudge_text": "",
      "unlocking_nudge_text_v2": "",
      "has_srt": false,
      "has_liked": false,
      "seek_position": 0,
      "can_download": true,
      "is_downloaded": false,
      "is_self": false,
      "unlock_type": "subscription",
      "transcript": {}
    },
    {
      "id": 671154,
      "title": "vishnupuranam Ep 25 new",
      "slug": "vishnupuranam-ep-25-new",
      "status": "live",
      "image": "https://images.cdn.kukufm.com/f:webp/https://s3.ap-south-1.amazonaws.com/kukufm/channel_icons/079c93f521434619a89b7d525b9643c7.png",
      "original_image": "https://s3.ap-south-1.amazonaws.com/kukufm/channel_icons/079c93f521434619a89b7d525b9643c7.png",
      "duration_s": 502,
      "image_sizes": {
        "100": "https://images.cdn.kukufm.com/w:100/f:webp/q:85/https://s3.ap-south-1.amazonaws.com/kukufm/channel_icons/079c93f521434619a89b7d525b9643c7.png",
        "150": "https://images.cdn.kukufm.com/w:150/f:webp/q:85/https://s3.ap-south-1.amazonaws.com/kukufm/channel_icons/079c93f521434619a89b7d525b9643c7.png",
        "200": "https://images.cdn.kukufm.com/w:200/f:webp/q:85/https://s3.ap-south-1.amazonaws.com/kukufm/channel_icons/079c93f521434619a89b7d525b9643c7.png",
        "300": "https://images.cdn.kukufm.com/w:300/f:webp/q:85/https://s3.ap-south-1.amazonaws.com/kukufm/channel_icons/079c93f521434619a89b7d525b9643c7.png"
      },
      "n_likes": 0,
      "n_shares": 0,
      "n_plays": null,
      "n_listens": 1137,
      "n_comments": 0,
      "cover_type": null,
      "content": {
        "converted_hls_url": "https://kukufm.akamaized.net/audio/9055b054-0f68-4842-84c9-46e9354f3819.m3u8",
        "audio_128kb": "https://kukufm.akamaized.net/audio/9055b054-0f68-4842-84c9-46e9354f3819128kb.m3u8",
        "audio_64kb": "https://kukufm.akamaized.net/audio/9055b054-0f68-4842-84c9-46e9354f381964kb.m3u8",
        "audio_24kb": "https://kukufm.akamaized.net/audio/9055b054-0f68-4842-84c9-46e9354f381924kb.m3u8"
      },
      "dynamic_link": "https://applinks.kukufm.com/yWZpiYEbRtUVYHeK9",
      "is_premium": true,
      "is_play_locked": false,
      "is_locked": true,
      "is_fictional": false,
      "index": 26,
      "show_id": 201794,
      "season_no": 1,
      "is_demo_premium": false,
      "is_free_unlocked": true,
      "media_size": 10416280,
      "published_on": "2023-08-04T05:18:15.594728+00:00",
      "thumbnail_image": "https://images.cdn.kukufm.com/w:200/f:jpg/q:85/https://s3.ap-south-1.amazonaws.com/kukufm/channel_icons/079c93f521434619a89b7d525b9643c7.png",
      "web_uri": "/episode/vishnupuranam-ep-25-new",
      "view_type": "default",
      "unlocking_nudge_text": "",
      "unlocking_nudge_text_v2": "",
      "has_srt": false,
      "has_liked": false,
      "seek_position": 0,
      "can_download": true,
      "is_downloaded": false,
      "is_self": false,
      "unlock_type": "subscription",
      "transcript": {}
    },
    {
      "id": 671155,
      "title": "vishnupuranam Ep 26",
      "slug": "vishnupuranam-ep-26",
      "status": "live",
      "image": "https://images.cdn.kukufm.com/f:webp/https://s3.ap-south-1.amazonaws.com/kukufm/channel_icons/079c93f521434619a89b7d525b9643c7.png",
      "original_image": "https://s3.ap-south-1.amazonaws.com/kukufm/channel_icons/079c93f521434619a89b7d525b9643c7.png",
      "duration_s": 488,
      "image_sizes": {
        "100": "https://images.cdn.kukufm.com/w:100/f:webp/q:85/https://s3.ap-south-1.amazonaws.com/kukufm/channel_icons/079c93f521434619a89b7d525b9643c7.png",
        "150": "https://images.cdn.kukufm.com/w:150/f:webp/q:85/https://s3.ap-south-1.amazonaws.com/kukufm/channel_icons/079c93f521434619a89b7d525b9643c7.png",
        "200": "https://images.cdn.kukufm.com/w:200/f:webp/q:85/https://s3.ap-south-1.amazonaws.com/kukufm/channel_icons/079c93f521434619a89b7d525b9643c7.png",
        "300": "https://images.cdn.kukufm.com/w:300/f:webp/q:85/https://s3.ap-south-1.amazonaws.com/kukufm/channel_icons/079c93f521434619a89b7d525b9643c7.png"
      },
      "n_likes": 0,
      "n_shares": 0,
      "n_plays": null,
      "n_listens": 1132,
      "n_comments": 0,
      "cover_type": null,
      "content": {
        "converted_hls_url": "https://kukufm.akamaized.net/audio/29849f95-2c5a-4bc1-9b13-3855276f86c2.m3u8",
        "audio_128kb": "https://kukufm.akamaized.net/audio/29849f95-2c5a-4bc1-9b13-3855276f86c2128kb.m3u8",
        "audio_64kb": "https://kukufm.akamaized.net/audio/29849f95-2c5a-4bc1-9b13-3855276f86c264kb.m3u8",
        "audio_24kb": "https://kukufm.akamaized.net/audio/29849f95-2c5a-4bc1-9b13-3855276f86c224kb.m3u8"
      },
      "dynamic_link": "https://applinks.kukufm.com/SAxKKxdsvLE6vyQK6",
      "is_premium": true,
      "is_play_locked": false,
      "is_locked": true,
      "is_fictional": false,
      "index": 27,
      "show_id": 201794,
      "season_no": 1,
      "is_demo_premium": false,
      "is_free_unlocked": true,
      "media_size": 10628767,
      "published_on": "2023-08-04T05:18:15.594728+00:00",
      "thumbnail_image": "https://images.cdn.kukufm.com/w:200/f:jpg/q:85/https://s3.ap-south-1.amazonaws.com/kukufm/channel_icons/079c93f521434619a89b7d525b9643c7.png",
      "web_uri": "/episode/vishnupuranam-ep-26",
      "view_type": "default",
      "unlocking_nudge_text": "",
      "unlocking_nudge_text_v2": "",
      "has_srt": false,
      "has_liked": false,
      "seek_position": 0,
      "can_download": true,
      "is_downloaded": false,
      "is_self": false,
      "unlock_type": "subscription",
      "transcript": {}
    },
    {
      "id": 671156,
      "title": "vishnupuranam Ep 27 new",
      "slug": "vishnupuranam-ep-27-new",
      "status": "live",
      "image": "https://images.cdn.kukufm.com/f:webp/https://s3.ap-south-1.amazonaws.com/kukufm/channel_icons/079c93f521434619a89b7d525b9643c7.png",
      "original_image": "https://s3.ap-south-1.amazonaws.com/kukufm/channel_icons/079c93f521434619a89b7d525b9643c7.png",
      "duration_s": 658,
      "image_sizes": {
        "100": "https://images.cdn.kukufm.com/w:100/f:webp/q:85/https://s3.ap-south-1.amazonaws.com/kukufm/channel_icons/079c93f521434619a89b7d525b9643c7.png",
        "150": "https://images.cdn.kukufm.com/w:150/f:webp/q:85/https://s3.ap-south-1.amazonaws.com/kukufm/channel_icons/079c93f521434619a89b7d525b9643c7.png",
        "200": "https://images.cdn.kukufm.com/w:200/f:webp/q:85/https://s3.ap-south-1.amazonaws.com/kukufm/channel_icons/079c93f521434619a89b7d525b9643c7.png",
        "300": "https://images.cdn.kukufm.com/w:300/f:webp/q:85/https://s3.ap-south-1.amazonaws.com/kukufm/channel_icons/079c93f521434619a89b7d525b9643c7.png"
      },
      "n_likes": 0,
      "n_shares": 0,
      "n_plays": null,
      "n_listens": 1165,
      "n_comments": 0,
      "cover_type": null,
      "content": {
        "converted_hls_url": "https://kukufm.akamaized.net/audio/e3608cbc-eb8d-470e-a840-2b3968cb9a87.m3u8",
        "audio_128kb": "https://kukufm.akamaized.net/audio/e3608cbc-eb8d-470e-a840-2b3968cb9a87128kb.m3u8",
        "audio_64kb": "https://kukufm.akamaized.net/audio/e3608cbc-eb8d-470e-a840-2b3968cb9a8764kb.m3u8",
        "audio_24kb": "https://kukufm.akamaized.net/audio/e3608cbc-eb8d-470e-a840-2b3968cb9a8724kb.m3u8"
      },
      "dynamic_link": "https://applinks.kukufm.com/3rvGRyQA5gCEdDt6A",
      "is_premium": true,
      "is_play_locked": false,
      "is_locked": true,
      "is_fictional": false,
      "index": 28,
      "show_id": 201794,
      "season_no": 1,
      "is_demo_premium": false,
      "is_free_unlocked": true,
      "media_size": 13771797,
      "published_on": "2023-08-04T05:18:15.594728+00:00",
      "thumbnail_image": "https://images.cdn.kukufm.com/w:200/f:jpg/q:85/https://s3.ap-south-1.amazonaws.com/kukufm/channel_icons/079c93f521434619a89b7d525b9643c7.png",
      "web_uri": "/episode/vishnupuranam-ep-27-new",
      "view_type": "default",
      "unlocking_nudge_text": "",
      "unlocking_nudge_text_v2": "",
      "has_srt": false,
      "has_liked": false,
      "seek_position": 0,
      "can_download": true,
      "is_downloaded": false,
      "is_self": false,
      "unlock_type": "subscription",
      "transcript": {}
    },
    {
      "id": 671157,
      "title": "vishnupuranam Ep 28 new",
      "slug": "vishnupuranam-ep-28-new",
      "status": "live",
      "image": "https://images.cdn.kukufm.com/f:webp/https://s3.ap-south-1.amazonaws.com/kukufm/channel_icons/079c93f521434619a89b7d525b9643c7.png",
      "original_image": "https://s3.ap-south-1.amazonaws.com/kukufm/channel_icons/079c93f521434619a89b7d525b9643c7.png",
      "duration_s": 757,
      "image_sizes": {
        "100": "https://images.cdn.kukufm.com/w:100/f:webp/q:85/https://s3.ap-south-1.amazonaws.com/kukufm/channel_icons/079c93f521434619a89b7d525b9643c7.png",
        "150": "https://images.cdn.kukufm.com/w:150/f:webp/q:85/https://s3.ap-south-1.amazonaws.com/kukufm/channel_icons/079c93f521434619a89b7d525b9643c7.png",
        "200": "https://images.cdn.kukufm.com/w:200/f:webp/q:85/https://s3.ap-south-1.amazonaws.com/kukufm/channel_icons/079c93f521434619a89b7d525b9643c7.png",
        "300": "https://images.cdn.kukufm.com/w:300/f:webp/q:85/https://s3.ap-south-1.amazonaws.com/kukufm/channel_icons/079c93f521434619a89b7d525b9643c7.png"
      },
      "n_likes": 0,
      "n_shares": 0,
      "n_plays": null,
      "n_listens": 1251,
      "n_comments": 3,
      "cover_type": null,
      "content": {
        "converted_hls_url": "https://kukufm.akamaized.net/audio/7b5b3c08-f2b8-4617-a979-8452c5244571.m3u8",
        "audio_128kb": "https://kukufm.akamaized.net/audio/7b5b3c08-f2b8-4617-a979-8452c5244571128kb.m3u8",
        "audio_64kb": "https://kukufm.akamaized.net/audio/7b5b3c08-f2b8-4617-a979-8452c524457164kb.m3u8",
        "audio_24kb": "https://kukufm.akamaized.net/audio/7b5b3c08-f2b8-4617-a979-8452c524457124kb.m3u8"
      },
      "dynamic_link": "https://applinks.kukufm.com/sx8GDsFZb1ReFq477",
      "is_premium": true,
      "is_play_locked": false,
      "is_locked": true,
      "is_fictional": false,
      "index": 29,
      "show_id": 201794,
      "season_no": 1,
      "is_demo_premium": false,
      "is_free_unlocked": true,
      "media_size": 16094650,
      "published_on": "2023-08-04T05:18:15.594728+00:00",
      "thumbnail_image": "https://images.cdn.kukufm.com/w:200/f:jpg/q:85/https://s3.ap-south-1.amazonaws.com/kukufm/channel_icons/079c93f521434619a89b7d525b9643c7.png",
      "web_uri": "/episode/vishnupuranam-ep-28-new",
      "view_type": "default",
      "unlocking_nudge_text": "",
      "unlocking_nudge_text_v2": "",
      "has_srt": false,
      "has_liked": false,
      "seek_position": 0,
      "can_download": true,
      "is_downloaded": false,
      "is_self": false,
      "unlock_type": "subscription",
      "transcript": {}
    }
  ],
  "has_more": false,
  "n_episodes": 29,
  "n_pages": 1,
  "page": 1,
  "support_sticker": "",
  "is_skip_show_page": false,
  "season_n_episodes": 29,
  "last_unlocked_episode_index": 1,
  "first_locked_episode_title": "1. Puranam sollapatta kadhai",
  "seo_description": "",
  "ads_info": {
    "interstitial_unit_id": "ca-app-pub-4561182393559685/8104245285",
    "reward_unit_id": "ca-app-pub-4561182393559685/3766806802"
  }
}