{
  "show": {
    "id": 195753,
    "slug": "what-is-governorr-role-in-state-administration",
    "title": "What Is Governor's Role In State Administration ",
    "image": "https://images.cdn.kukufm.com/f:webp/https://s3.ap-south-1.amazonaws.com/kukufm/channel_icons/26c479db05654e44b6c84bde130aaa91.png",
    "original_image": "https://s3.ap-south-1.amazonaws.com/kukufm/channel_icons/26c479db05654e44b6c84bde130aaa91.png",
    "image_sizes": {
      "100": "https://images.cdn.kukufm.com/w:100/f:webp/q:85/https://s3.ap-south-1.amazonaws.com/kukufm/channel_icons/26c479db05654e44b6c84bde130aaa91.png",
      "200": "https://images.cdn.kukufm.com/w:200/f:webp/q:85/https://s3.ap-south-1.amazonaws.com/kukufm/channel_icons/26c479db05654e44b6c84bde130aaa91.png",
      "300": "https://images.cdn.kukufm.com/w:300/f:webp/q:85/https://s3.ap-south-1.amazonaws.com/kukufm/channel_icons/26c479db05654e44b6c84bde130aaa91.png"
    },
    "language": "tamil",
    "published_on": "2023-04-19T07:40:04.349362+00:00",
    "status": "live",
    "n_listens": 11236,
    "is_verified": false,
    "dynamic_link": null,
    "uri": "app://kukufm/show/what-is-governorr-role-in-state-administration/",
    "web_uri": "/show/what-is-governorr-role-in-state-administration",
    "share_image_url": "https://images.cdn.kukufm.com/w:300/f:webp/q:85/https://s3.ap-south-1.amazonaws.com/kukufm/channel_icons/26c479db05654e44b6c84bde130aaa91.png",
    "cover_type": null,
    "is_premium": true,
    "overall_rating": 4.384,
    "n_reviews": 19,
    "is_fictional": false,
    "duration_s": 4764,
    "n_episodes": 10,
    "n_comments": 0,
    "is_transcript_available": null,
    "n_impressions": 0,
    "recommendation_score": 0,
    "users_completion_p": 0,
    "daily_unlock_count": 0,
    "thumbnail_color": "#33b29f81",
    "is_daily_unlock_enabled": false,
    "n_seasons": 1,
    "is_coin_based": false,
    "monetization_type": "subscription",
    "is_coin_premium": false,
    "show_label_info": {},
    "is_coming_soon": null,
    "show_type": "cu_show",
    "is_comments_exposure_enabled": false,
    "is_adult_content": false,
    "sharing_text": "हेलो! मैंने कुकू एफएम पर इस शो को सुना और मेरे ख्‍याल से आपको भी पसंद आएगा",
    "sharing_text_v2": "हेलो! मैंने Kuku FM (Android)  पर यह शो सुना और मुझे यकीन है कि आपको भी यह जरूर पसंद आएगा। \nhttps://links.kukufm.com/NW4Ubz",
    "completion_status": 1,
    "description": "Oru Aalunar oda poruppugal enna, avarakku kudkkapatta power enna nu indha audio book la kelunga. ",
    "description_secondary": "Oru Aalunar oda poruppugal enna, avarakku kudkkapatta power enna nu indha audio book la kelunga. ",
    "author": {
      "id": 28287293,
      "name": "Booshitha",
      "avatar_cdn": "https://images.cdn.kukufm.com/https://kukufm.s3.amazonaws.com/avatars/5c7aa638f3394365a3f7b449c36e3a39.png",
      "original_avatar": "https://kukufm.s3.amazonaws.com/avatars/5c7aa638f3394365a3f7b449c36e3a39.png",
      "avatar": {
        "32": "https://images.cdn.kukufm.com/w:32/f:jpg/q:90/https://kukufm.s3.amazonaws.com/avatars/5c7aa638f3394365a3f7b449c36e3a39.png",
        "64": "https://images.cdn.kukufm.com/w:64/f:jpg/q:90/https://kukufm.s3.amazonaws.com/avatars/5c7aa638f3394365a3f7b449c36e3a39.png",
        "128": "https://images.cdn.kukufm.com/w:128/f:jpg/q:90/https://kukufm.s3.amazonaws.com/avatars/5c7aa638f3394365a3f7b449c36e3a39.png",
        "256": "https://images.cdn.kukufm.com/w:256/f:jpg/q:90/https://kukufm.s3.amazonaws.com/avatars/5c7aa638f3394365a3f7b449c36e3a39.png"
      },
      "bio": "Play What You Love",
      "incognito_mode": false
    },
    "lang": {
      "id": 8,
      "title": "தமிழ்",
      "title_secondary": "Tamil",
      "image": "https://images.cdn.kukufm.com/https://kukufm.s3.ap-south-1.amazonaws.com/icons/tamil_2.png",
      "slug": "tamil",
      "color": "#282E34",
      "uri": "app://kukufm/home-lang/tamil",
      "web_uri": "/home-lang/tamil",
      "color_info": {
        "bg_color": "#EBCEF5",
        "text_color": "#671584"
      },
      "short_title": "த",
      "svg_icon": "https://d1l07mcd18xic4.cloudfront.net/lang_icons/tamil.svg",
      "icon_sizes": {
        "16": "https://images.cdn.kukufm.com/w:16/q:85/https://kukufm.s3.ap-south-1.amazonaws.com/icons/tamil_2.png",
        "64": "https://images.cdn.kukufm.com/w:64/q:85/https://kukufm.s3.ap-south-1.amazonaws.com/icons/tamil_2.png",
        "256": "https://images.cdn.kukufm.com/w:256/q:85/https://kukufm.s3.ap-south-1.amazonaws.com/icons/tamil_2.png"
      }
    },
    "content_type": {
      "id": 12,
      "title": "फुल बुक्‍स",
      "slug": "audio-book",
      "uri": "app://kukufm/content-types/audio-book",
      "web_uri": "/content-types/audio-book",
      "color_info": {
        "bg_color": "#40C2B3",
        "text_color": "#40C2B3"
      }
    },
    "other_images": {
      "landscape_image": "https://images.cdn.kukufm.com/f:webp/https://s3.ap-south-1.amazonaws.com/kukufm/channel_icons/2bb965410f0e4a3fbf7f54adcbbecba4_landscape_56.jpg",
      "landscape_image_sizes": {
        "360": "https://images.cdn.kukufm.com/w:360/f:webp/q:85/https://s3.ap-south-1.amazonaws.com/kukufm/channel_icons/2bb965410f0e4a3fbf7f54adcbbecba4_landscape_56.jpg",
        "480": "https://images.cdn.kukufm.com/w:480/f:webp/q:85/https://s3.ap-south-1.amazonaws.com/kukufm/channel_icons/2bb965410f0e4a3fbf7f54adcbbecba4_landscape_56.jpg",
        "720": "https://images.cdn.kukufm.com/w:720/f:webp/q:85/https://s3.ap-south-1.amazonaws.com/kukufm/channel_icons/2bb965410f0e4a3fbf7f54adcbbecba4_landscape_56.jpg"
      },
      "vertical_thumbnail": null,
      "vertical_thumbnail_image_sizes": {
        "360": "https://images.cdn.kukufm.com/w:360/f:webp/q:85/https://s3.ap-south-1.amazonaws.com/kukufm/channel_icons/26c479db05654e44b6c84bde130aaa91.png",
        "480": "https://images.cdn.kukufm.com/w:480/f:webp/q:85/https://s3.ap-south-1.amazonaws.com/kukufm/channel_icons/26c479db05654e44b6c84bde130aaa91.png",
        "720": "https://images.cdn.kukufm.com/w:720/f:webp/q:85/https://s3.ap-south-1.amazonaws.com/kukufm/channel_icons/26c479db05654e44b6c84bde130aaa91.png"
      }
    },
    "thumbnail_data": {},
    "labels": [
      "All Episodes",
      "13+"
    ],
    "is_top_10": false,
    "is_reel": false,
    "ever_been_vip_show": false,
    "resume_episode": {
      "id": 636209,
      "title": "Per arasar  oda kadhai",
      "slug": "governor-intro",
      "status": "live",
      "image": "https://images.cdn.kukufm.com/f:webp/https://s3.ap-south-1.amazonaws.com/kukufm/channel_icons/26c479db05654e44b6c84bde130aaa91.png",
      "original_image": "https://s3.ap-south-1.amazonaws.com/kukufm/channel_icons/26c479db05654e44b6c84bde130aaa91.png",
      "duration_s": 221,
      "image_sizes": {
        "100": "https://images.cdn.kukufm.com/w:100/f:webp/q:85/https://s3.ap-south-1.amazonaws.com/kukufm/channel_icons/26c479db05654e44b6c84bde130aaa91.png",
        "150": "https://images.cdn.kukufm.com/w:150/f:webp/q:85/https://s3.ap-south-1.amazonaws.com/kukufm/channel_icons/26c479db05654e44b6c84bde130aaa91.png",
        "200": "https://images.cdn.kukufm.com/w:200/f:webp/q:85/https://s3.ap-south-1.amazonaws.com/kukufm/channel_icons/26c479db05654e44b6c84bde130aaa91.png",
        "300": "https://images.cdn.kukufm.com/w:300/f:webp/q:85/https://s3.ap-south-1.amazonaws.com/kukufm/channel_icons/26c479db05654e44b6c84bde130aaa91.png"
      },
      "n_likes": 0,
      "n_shares": 0,
      "n_plays": 3468,
      "n_listens": 3468,
      "n_comments": 1,
      "cover_type": null,
      "content": {
        "url": "https://d1l07mcd18xic4.cloudfront.net/audio/8eaeb734-dced-4bb1-b5bf-9de51e88abcefull.mp4",
        "hls_url": "https://d1l07mcd18xic4.cloudfront.net/audio/8eaeb734-dced-4bb1-b5bf-9de51e88abce.m3u8"
      },
      "dynamic_link": "https://applinks.kukufm.com/RvzW1ho946G9Vb986",
      "is_premium": true,
      "is_play_locked": false,
      "is_locked": false,
      "is_fictional": false,
      "index": 1,
      "show_id": 195753,
      "season_no": 1,
      "is_demo_premium": true,
      "media_size": 4937848,
      "published_on": "2023-04-19T07:38:55.106211+00:00",
      "thumbnail_image": "https://images.cdn.kukufm.com/w:200/f:jpg/q:85/https://s3.ap-south-1.amazonaws.com/kukufm/channel_icons/26c479db05654e44b6c84bde130aaa91.png"
    },
    "is_self": false,
    "ad_enabled": false,
    "can_download_all": true,
    "is_added": false,
    "genre": {
      "id": 118,
      "title": "इंफॉर्मेशन",
      "slug": "information",
      "uri": "app://app/genres/information",
      "web_uri": "/genres/information"
    },
    "credits": {
      "production_houses": [
        {
          "id": 38979903,
          "full_name": "F Media",
          "avatar": {
            "16": "https://images.cdn.kukufm.com/w:16/q:85/https://kukufm.s3.amazonaws.com/avatars/45cde8e1b2bf47cf95d5b231f88e1c34.png",
            "64": "https://images.cdn.kukufm.com/w:64/q:85/https://kukufm.s3.amazonaws.com/avatars/45cde8e1b2bf47cf95d5b231f88e1c34.png",
            "256": "https://images.cdn.kukufm.com/w:256/q:85/https://kukufm.s3.amazonaws.com/avatars/45cde8e1b2bf47cf95d5b231f88e1c34.png"
          },
          "n_followers": 207,
          "contribution_type": "production_house",
          "is_primary_creator": true,
          "is_followed": false
        }
      ],
      "directors": [
        {
          "id": 28287293,
          "full_name": "Booshitha",
          "avatar": {
            "16": "https://images.cdn.kukufm.com/w:16/q:85/https://kukufm.s3.amazonaws.com/avatars/5c7aa638f3394365a3f7b449c36e3a39.png",
            "64": "https://images.cdn.kukufm.com/w:64/q:85/https://kukufm.s3.amazonaws.com/avatars/5c7aa638f3394365a3f7b449c36e3a39.png",
            "256": "https://images.cdn.kukufm.com/w:256/q:85/https://kukufm.s3.amazonaws.com/avatars/5c7aa638f3394365a3f7b449c36e3a39.png"
          },
          "n_followers": 1626,
          "contribution_type": "director",
          "is_primary_creator": true,
          "is_followed": false
        }
      ],
      "writers": [
        {
          "id": 38979903,
          "full_name": "F Media",
          "avatar": {
            "16": "https://images.cdn.kukufm.com/w:16/q:85/https://kukufm.s3.amazonaws.com/avatars/45cde8e1b2bf47cf95d5b231f88e1c34.png",
            "64": "https://images.cdn.kukufm.com/w:64/q:85/https://kukufm.s3.amazonaws.com/avatars/45cde8e1b2bf47cf95d5b231f88e1c34.png",
            "256": "https://images.cdn.kukufm.com/w:256/q:85/https://kukufm.s3.amazonaws.com/avatars/45cde8e1b2bf47cf95d5b231f88e1c34.png"
          },
          "n_followers": 207,
          "contribution_type": "writer",
          "is_primary_creator": true,
          "is_followed": false
        }
      ],
      "voice_artists": [
        {
          "id": 38979903,
          "full_name": "F Media",
          "avatar": {
            "16": "https://images.cdn.kukufm.com/w:16/q:85/https://kukufm.s3.amazonaws.com/avatars/45cde8e1b2bf47cf95d5b231f88e1c34.png",
            "64": "https://images.cdn.kukufm.com/w:64/q:85/https://kukufm.s3.amazonaws.com/avatars/45cde8e1b2bf47cf95d5b231f88e1c34.png",
            "256": "https://images.cdn.kukufm.com/w:256/q:85/https://kukufm.s3.amazonaws.com/avatars/45cde8e1b2bf47cf95d5b231f88e1c34.png"
          },
          "n_followers": 207,
          "contribution_type": "voice_artist",
          "is_primary_creator": false,
          "is_followed": false
        },
        {
          "id": 29309059,
          "full_name": "Kutty karthi",
          "avatar": {
            "16": "https://images.cdn.kukufm.com/w:16/q:85/https://kukufm.s3.amazonaws.com/avatars/9dcb227e5b104a2196c9f533ddd3b465.jpg",
            "64": "https://images.cdn.kukufm.com/w:64/q:85/https://kukufm.s3.amazonaws.com/avatars/9dcb227e5b104a2196c9f533ddd3b465.jpg",
            "256": "https://images.cdn.kukufm.com/w:256/q:85/https://kukufm.s3.amazonaws.com/avatars/9dcb227e5b104a2196c9f533ddd3b465.jpg"
          },
          "n_followers": 3,
          "contribution_type": "voice_artist",
          "is_primary_creator": false,
          "is_followed": false
        }
      ]
    },
    "media_size": 103399360,
    "is_play_locked": false,
    "hide_download_all_icon": null,
    "last_unlocked_episode_index": 1,
    "first_locked_episode_title": "1. Uruvaana kadhai",
    "growth_engine_audio_cue_info": {},
    "social_proofing": {
      "review": null
    },
    "physical_book_data": {},
    "show_unlocked_nudge_text": "Unlocked with Premium"
  },
  "episodes": [
    {
      "id": 636209,
      "title": "Per arasar  oda kadhai",
      "slug": "governor-intro",
      "status": "live",
      "image": "https://images.cdn.kukufm.com/f:webp/https://s3.ap-south-1.amazonaws.com/kukufm/channel_icons/26c479db05654e44b6c84bde130aaa91.png",
      "original_image": "https://s3.ap-south-1.amazonaws.com/kukufm/channel_icons/26c479db05654e44b6c84bde130aaa91.png",
      "duration_s": 221,
      "image_sizes": {
        "100": "https://images.cdn.kukufm.com/w:100/f:webp/q:85/https://s3.ap-south-1.amazonaws.com/kukufm/channel_icons/26c479db05654e44b6c84bde130aaa91.png",
        "150": "https://images.cdn.kukufm.com/w:150/f:webp/q:85/https://s3.ap-south-1.amazonaws.com/kukufm/channel_icons/26c479db05654e44b6c84bde130aaa91.png",
        "200": "https://images.cdn.kukufm.com/w:200/f:webp/q:85/https://s3.ap-south-1.amazonaws.com/kukufm/channel_icons/26c479db05654e44b6c84bde130aaa91.png",
        "300": "https://images.cdn.kukufm.com/w:300/f:webp/q:85/https://s3.ap-south-1.amazonaws.com/kukufm/channel_icons/26c479db05654e44b6c84bde130aaa91.png"
      },
      "n_likes": 0,
      "n_shares": 0,
      "n_plays": null,
      "n_listens": 3468,
      "n_comments": 1,
      "cover_type": null,
      "content": {
        "converted_hls_url": "https://kukufm.akamaized.net/audio/8eaeb734-dced-4bb1-b5bf-9de51e88abce.m3u8",
        "audio_128kb": "https://kukufm.akamaized.net/audio/8eaeb734-dced-4bb1-b5bf-9de51e88abce128kb.m3u8",
        "audio_64kb": "https://kukufm.akamaized.net/audio/8eaeb734-dced-4bb1-b5bf-9de51e88abce64kb.m3u8",
        "audio_24kb": "https://kukufm.akamaized.net/audio/8eaeb734-dced-4bb1-b5bf-9de51e88abce24kb.m3u8"
      },
      "dynamic_link": "https://applinks.kukufm.com/RvzW1ho946G9Vb986",
      "is_premium": true,
      "is_play_locked": false,
      "is_locked": false,
      "is_fictional": false,
      "index": 1,
      "show_id": 195753,
      "season_no": 1,
      "is_demo_premium": true,
      "media_size": 4937848,
      "published_on": "2023-04-19T07:38:55.106211+00:00",
      "thumbnail_image": "https://images.cdn.kukufm.com/w:200/f:jpg/q:85/https://s3.ap-south-1.amazonaws.com/kukufm/channel_icons/26c479db05654e44b6c84bde130aaa91.png",
      "web_uri": "/episode/governor-intro",
      "view_type": "default",
      "unlocking_nudge_text": "",
      "unlocking_nudge_text_v2": "",
      "has_srt": false,
      "has_liked": false,
      "seek_position": 0,
      "can_download": true,
      "is_downloaded": false,
      "is_self": false,
      "unlock_type": "subscription",
      "transcript": {}
    },
    {
      "id": 636202,
      "title": "1. Uruvaana kadhai",
      "slug": "governor-01",
      "status": "live",
      "image": "https://images.cdn.kukufm.com/f:webp/https://s3.ap-south-1.amazonaws.com/kukufm/channel_icons/26c479db05654e44b6c84bde130aaa91.png",
      "original_image": "https://s3.ap-south-1.amazonaws.com/kukufm/channel_icons/26c479db05654e44b6c84bde130aaa91.png",
      "duration_s": 574,
      "image_sizes": {
        "100": "https://images.cdn.kukufm.com/w:100/f:webp/q:85/https://s3.ap-south-1.amazonaws.com/kukufm/channel_icons/26c479db05654e44b6c84bde130aaa91.png",
        "150": "https://images.cdn.kukufm.com/w:150/f:webp/q:85/https://s3.ap-south-1.amazonaws.com/kukufm/channel_icons/26c479db05654e44b6c84bde130aaa91.png",
        "200": "https://images.cdn.kukufm.com/w:200/f:webp/q:85/https://s3.ap-south-1.amazonaws.com/kukufm/channel_icons/26c479db05654e44b6c84bde130aaa91.png",
        "300": "https://images.cdn.kukufm.com/w:300/f:webp/q:85/https://s3.ap-south-1.amazonaws.com/kukufm/channel_icons/26c479db05654e44b6c84bde130aaa91.png"
      },
      "n_likes": 0,
      "n_shares": 0,
      "n_plays": null,
      "n_listens": 2029,
      "n_comments": 0,
      "cover_type": null,
      "content": {
        "converted_hls_url": "https://kukufm.akamaized.net/audio/ec439d70-a5ac-4c8b-a5ca-1bc6bc86c562.m3u8",
        "audio_128kb": "https://kukufm.akamaized.net/audio/ec439d70-a5ac-4c8b-a5ca-1bc6bc86c562128kb.m3u8",
        "audio_64kb": "https://kukufm.akamaized.net/audio/ec439d70-a5ac-4c8b-a5ca-1bc6bc86c56264kb.m3u8",
        "audio_24kb": "https://kukufm.akamaized.net/audio/ec439d70-a5ac-4c8b-a5ca-1bc6bc86c56224kb.m3u8"
      },
      "dynamic_link": "https://applinks.kukufm.com/hZCeQNHBcsSJMsyPA",
      "is_premium": true,
      "is_play_locked": false,
      "is_locked": true,
      "is_fictional": false,
      "index": 2,
      "show_id": 195753,
      "season_no": 1,
      "is_demo_premium": false,
      "is_free_unlocked": true,
      "media_size": 12649809,
      "published_on": "2023-04-19T07:38:55.106211+00:00",
      "thumbnail_image": "https://images.cdn.kukufm.com/w:200/f:jpg/q:85/https://s3.ap-south-1.amazonaws.com/kukufm/channel_icons/26c479db05654e44b6c84bde130aaa91.png",
      "web_uri": "/episode/governor-01",
      "view_type": "default",
      "unlocking_nudge_text": "",
      "unlocking_nudge_text_v2": "",
      "has_srt": false,
      "has_liked": false,
      "seek_position": 0,
      "can_download": true,
      "is_downloaded": false,
      "is_self": false,
      "unlock_type": "subscription",
      "transcript": {}
    },
    {
      "id": 636201,
      "title": "2. Adhigaarangal & seyalpaadugal",
      "slug": "governor-02",
      "status": "live",
      "image": "https://images.cdn.kukufm.com/f:webp/https://s3.ap-south-1.amazonaws.com/kukufm/channel_icons/26c479db05654e44b6c84bde130aaa91.png",
      "original_image": "https://s3.ap-south-1.amazonaws.com/kukufm/channel_icons/26c479db05654e44b6c84bde130aaa91.png",
      "duration_s": 695,
      "image_sizes": {
        "100": "https://images.cdn.kukufm.com/w:100/f:webp/q:85/https://s3.ap-south-1.amazonaws.com/kukufm/channel_icons/26c479db05654e44b6c84bde130aaa91.png",
        "150": "https://images.cdn.kukufm.com/w:150/f:webp/q:85/https://s3.ap-south-1.amazonaws.com/kukufm/channel_icons/26c479db05654e44b6c84bde130aaa91.png",
        "200": "https://images.cdn.kukufm.com/w:200/f:webp/q:85/https://s3.ap-south-1.amazonaws.com/kukufm/channel_icons/26c479db05654e44b6c84bde130aaa91.png",
        "300": "https://images.cdn.kukufm.com/w:300/f:webp/q:85/https://s3.ap-south-1.amazonaws.com/kukufm/channel_icons/26c479db05654e44b6c84bde130aaa91.png"
      },
      "n_likes": 0,
      "n_shares": 0,
      "n_plays": null,
      "n_listens": 1373,
      "n_comments": 2,
      "cover_type": null,
      "content": {
        "converted_hls_url": "https://kukufm.akamaized.net/audio/2b5ef315-bbf3-46df-9a7f-1f1ed88bc9fe.m3u8",
        "audio_128kb": "https://kukufm.akamaized.net/audio/2b5ef315-bbf3-46df-9a7f-1f1ed88bc9fe128kb.m3u8",
        "audio_64kb": "https://kukufm.akamaized.net/audio/2b5ef315-bbf3-46df-9a7f-1f1ed88bc9fe64kb.m3u8",
        "audio_24kb": "https://kukufm.akamaized.net/audio/2b5ef315-bbf3-46df-9a7f-1f1ed88bc9fe24kb.m3u8"
      },
      "dynamic_link": "https://applinks.kukufm.com/a2tzQukkBdHrosDH9",
      "is_premium": true,
      "is_play_locked": false,
      "is_locked": true,
      "is_fictional": false,
      "index": 3,
      "show_id": 195753,
      "season_no": 1,
      "is_demo_premium": false,
      "is_free_unlocked": true,
      "media_size": 15065798,
      "published_on": "2023-04-19T07:38:55.106211+00:00",
      "thumbnail_image": "https://images.cdn.kukufm.com/w:200/f:jpg/q:85/https://s3.ap-south-1.amazonaws.com/kukufm/channel_icons/26c479db05654e44b6c84bde130aaa91.png",
      "web_uri": "/episode/governor-02",
      "view_type": "default",
      "unlocking_nudge_text": "",
      "unlocking_nudge_text_v2": "",
      "has_srt": false,
      "has_liked": false,
      "seek_position": 0,
      "can_download": true,
      "is_downloaded": false,
      "is_self": false,
      "unlock_type": "subscription",
      "transcript": {}
    },
    {
      "id": 636204,
      "title": "3. Sattam mattrum ozhungu",
      "slug": "governor-03",
      "status": "live",
      "image": "https://images.cdn.kukufm.com/f:webp/https://s3.ap-south-1.amazonaws.com/kukufm/channel_icons/26c479db05654e44b6c84bde130aaa91.png",
      "original_image": "https://s3.ap-south-1.amazonaws.com/kukufm/channel_icons/26c479db05654e44b6c84bde130aaa91.png",
      "duration_s": 517,
      "image_sizes": {
        "100": "https://images.cdn.kukufm.com/w:100/f:webp/q:85/https://s3.ap-south-1.amazonaws.com/kukufm/channel_icons/26c479db05654e44b6c84bde130aaa91.png",
        "150": "https://images.cdn.kukufm.com/w:150/f:webp/q:85/https://s3.ap-south-1.amazonaws.com/kukufm/channel_icons/26c479db05654e44b6c84bde130aaa91.png",
        "200": "https://images.cdn.kukufm.com/w:200/f:webp/q:85/https://s3.ap-south-1.amazonaws.com/kukufm/channel_icons/26c479db05654e44b6c84bde130aaa91.png",
        "300": "https://images.cdn.kukufm.com/w:300/f:webp/q:85/https://s3.ap-south-1.amazonaws.com/kukufm/channel_icons/26c479db05654e44b6c84bde130aaa91.png"
      },
      "n_likes": 0,
      "n_shares": 0,
      "n_plays": null,
      "n_listens": 989,
      "n_comments": 2,
      "cover_type": null,
      "content": {
        "converted_hls_url": "https://kukufm.akamaized.net/audio/007c638e-b71b-4e8c-8e97-177436674dc4.m3u8",
        "audio_128kb": "https://kukufm.akamaized.net/audio/007c638e-b71b-4e8c-8e97-177436674dc4128kb.m3u8",
        "audio_64kb": "https://kukufm.akamaized.net/audio/007c638e-b71b-4e8c-8e97-177436674dc464kb.m3u8",
        "audio_24kb": "https://kukufm.akamaized.net/audio/007c638e-b71b-4e8c-8e97-177436674dc424kb.m3u8"
      },
      "dynamic_link": "https://applinks.kukufm.com/BLZxfy2QKe7LAqyg6",
      "is_premium": true,
      "is_play_locked": false,
      "is_locked": true,
      "is_fictional": false,
      "index": 4,
      "show_id": 195753,
      "season_no": 1,
      "is_demo_premium": false,
      "is_free_unlocked": true,
      "media_size": 11018260,
      "published_on": "2023-04-19T07:38:55.106211+00:00",
      "thumbnail_image": "https://images.cdn.kukufm.com/w:200/f:jpg/q:85/https://s3.ap-south-1.amazonaws.com/kukufm/channel_icons/26c479db05654e44b6c84bde130aaa91.png",
      "web_uri": "/episode/governor-03",
      "view_type": "default",
      "unlocking_nudge_text": "",
      "unlocking_nudge_text_v2": "",
      "has_srt": false,
      "has_liked": false,
      "seek_position": 0,
      "can_download": true,
      "is_downloaded": false,
      "is_self": false,
      "unlock_type": "subscription",
      "transcript": {}
    },
    {
      "id": 636206,
      "title": "4. Aalunar'in pangu",
      "slug": "governor-04",
      "status": "live",
      "image": "https://images.cdn.kukufm.com/f:webp/https://s3.ap-south-1.amazonaws.com/kukufm/channel_icons/26c479db05654e44b6c84bde130aaa91.png",
      "original_image": "https://s3.ap-south-1.amazonaws.com/kukufm/channel_icons/26c479db05654e44b6c84bde130aaa91.png",
      "duration_s": 408,
      "image_sizes": {
        "100": "https://images.cdn.kukufm.com/w:100/f:webp/q:85/https://s3.ap-south-1.amazonaws.com/kukufm/channel_icons/26c479db05654e44b6c84bde130aaa91.png",
        "150": "https://images.cdn.kukufm.com/w:150/f:webp/q:85/https://s3.ap-south-1.amazonaws.com/kukufm/channel_icons/26c479db05654e44b6c84bde130aaa91.png",
        "200": "https://images.cdn.kukufm.com/w:200/f:webp/q:85/https://s3.ap-south-1.amazonaws.com/kukufm/channel_icons/26c479db05654e44b6c84bde130aaa91.png",
        "300": "https://images.cdn.kukufm.com/w:300/f:webp/q:85/https://s3.ap-south-1.amazonaws.com/kukufm/channel_icons/26c479db05654e44b6c84bde130aaa91.png"
      },
      "n_likes": 0,
      "n_shares": 0,
      "n_plays": null,
      "n_listens": 790,
      "n_comments": 1,
      "cover_type": null,
      "content": {
        "converted_hls_url": "https://kukufm.akamaized.net/audio/d4258ed0-9b27-4351-a688-f2e267b33087.m3u8",
        "audio_128kb": "https://kukufm.akamaized.net/audio/d4258ed0-9b27-4351-a688-f2e267b33087128kb.m3u8",
        "audio_64kb": "https://kukufm.akamaized.net/audio/d4258ed0-9b27-4351-a688-f2e267b3308764kb.m3u8",
        "audio_24kb": "https://kukufm.akamaized.net/audio/d4258ed0-9b27-4351-a688-f2e267b3308724kb.m3u8"
      },
      "dynamic_link": "https://applinks.kukufm.com/VAsv6NmPM8wSAfpq8",
      "is_premium": true,
      "is_play_locked": false,
      "is_locked": true,
      "is_fictional": false,
      "index": 5,
      "show_id": 195753,
      "season_no": 1,
      "is_demo_premium": false,
      "is_free_unlocked": true,
      "media_size": 8677598,
      "published_on": "2023-04-19T07:38:55.106211+00:00",
      "thumbnail_image": "https://images.cdn.kukufm.com/w:200/f:jpg/q:85/https://s3.ap-south-1.amazonaws.com/kukufm/channel_icons/26c479db05654e44b6c84bde130aaa91.png",
      "web_uri": "/episode/governor-04",
      "view_type": "default",
      "unlocking_nudge_text": "",
      "unlocking_nudge_text_v2": "",
      "has_srt": false,
      "has_liked": false,
      "seek_position": 0,
      "can_download": true,
      "is_downloaded": false,
      "is_self": false,
      "unlock_type": "subscription",
      "transcript": {}
    },
    {
      "id": 636200,
      "title": "5. Nidhi ",
      "slug": "governor-05",
      "status": "live",
      "image": "https://images.cdn.kukufm.com/f:webp/https://s3.ap-south-1.amazonaws.com/kukufm/channel_icons/26c479db05654e44b6c84bde130aaa91.png",
      "original_image": "https://s3.ap-south-1.amazonaws.com/kukufm/channel_icons/26c479db05654e44b6c84bde130aaa91.png",
      "duration_s": 641,
      "image_sizes": {
        "100": "https://images.cdn.kukufm.com/w:100/f:webp/q:85/https://s3.ap-south-1.amazonaws.com/kukufm/channel_icons/26c479db05654e44b6c84bde130aaa91.png",
        "150": "https://images.cdn.kukufm.com/w:150/f:webp/q:85/https://s3.ap-south-1.amazonaws.com/kukufm/channel_icons/26c479db05654e44b6c84bde130aaa91.png",
        "200": "https://images.cdn.kukufm.com/w:200/f:webp/q:85/https://s3.ap-south-1.amazonaws.com/kukufm/channel_icons/26c479db05654e44b6c84bde130aaa91.png",
        "300": "https://images.cdn.kukufm.com/w:300/f:webp/q:85/https://s3.ap-south-1.amazonaws.com/kukufm/channel_icons/26c479db05654e44b6c84bde130aaa91.png"
      },
      "n_likes": 0,
      "n_shares": 0,
      "n_plays": null,
      "n_listens": 746,
      "n_comments": 0,
      "cover_type": null,
      "content": {
        "converted_hls_url": "https://kukufm.akamaized.net/audio/369c9293-e454-4397-b0be-9ccd941d9af5.m3u8",
        "audio_128kb": "https://kukufm.akamaized.net/audio/369c9293-e454-4397-b0be-9ccd941d9af5128kb.m3u8",
        "audio_64kb": "https://kukufm.akamaized.net/audio/369c9293-e454-4397-b0be-9ccd941d9af564kb.m3u8",
        "audio_24kb": "https://kukufm.akamaized.net/audio/369c9293-e454-4397-b0be-9ccd941d9af524kb.m3u8"
      },
      "dynamic_link": "https://applinks.kukufm.com/ybb77hzCe6VHyh5CA",
      "is_premium": true,
      "is_play_locked": false,
      "is_locked": true,
      "is_fictional": false,
      "index": 6,
      "show_id": 195753,
      "season_no": 1,
      "is_demo_premium": false,
      "is_free_unlocked": true,
      "media_size": 13729528,
      "published_on": "2023-04-19T07:38:55.106211+00:00",
      "thumbnail_image": "https://images.cdn.kukufm.com/w:200/f:jpg/q:85/https://s3.ap-south-1.amazonaws.com/kukufm/channel_icons/26c479db05654e44b6c84bde130aaa91.png",
      "web_uri": "/episode/governor-05",
      "view_type": "default",
      "unlocking_nudge_text": "",
      "unlocking_nudge_text_v2": "",
      "has_srt": false,
      "has_liked": false,
      "seek_position": 0,
      "can_download": true,
      "is_downloaded": false,
      "is_self": false,
      "unlock_type": "subscription",
      "transcript": {}
    },
    {
      "id": 636208,
      "title": "6. Valarchi",
      "slug": "governor-06",
      "status": "live",
      "image": "https://images.cdn.kukufm.com/f:webp/https://s3.ap-south-1.amazonaws.com/kukufm/channel_icons/26c479db05654e44b6c84bde130aaa91.png",
      "original_image": "https://s3.ap-south-1.amazonaws.com/kukufm/channel_icons/26c479db05654e44b6c84bde130aaa91.png",
      "duration_s": 361,
      "image_sizes": {
        "100": "https://images.cdn.kukufm.com/w:100/f:webp/q:85/https://s3.ap-south-1.amazonaws.com/kukufm/channel_icons/26c479db05654e44b6c84bde130aaa91.png",
        "150": "https://images.cdn.kukufm.com/w:150/f:webp/q:85/https://s3.ap-south-1.amazonaws.com/kukufm/channel_icons/26c479db05654e44b6c84bde130aaa91.png",
        "200": "https://images.cdn.kukufm.com/w:200/f:webp/q:85/https://s3.ap-south-1.amazonaws.com/kukufm/channel_icons/26c479db05654e44b6c84bde130aaa91.png",
        "300": "https://images.cdn.kukufm.com/w:300/f:webp/q:85/https://s3.ap-south-1.amazonaws.com/kukufm/channel_icons/26c479db05654e44b6c84bde130aaa91.png"
      },
      "n_likes": 0,
      "n_shares": 0,
      "n_plays": null,
      "n_listens": 539,
      "n_comments": 0,
      "cover_type": null,
      "content": {
        "converted_hls_url": "https://kukufm.akamaized.net/audio/dd6e4a78-9211-4012-a854-fe93f4f0af24.m3u8",
        "audio_128kb": "https://kukufm.akamaized.net/audio/dd6e4a78-9211-4012-a854-fe93f4f0af24128kb.m3u8",
        "audio_64kb": "https://kukufm.akamaized.net/audio/dd6e4a78-9211-4012-a854-fe93f4f0af2464kb.m3u8",
        "audio_24kb": "https://kukufm.akamaized.net/audio/dd6e4a78-9211-4012-a854-fe93f4f0af2424kb.m3u8"
      },
      "dynamic_link": "https://applinks.kukufm.com/vge9p4nacoB32mxm9",
      "is_premium": true,
      "is_play_locked": false,
      "is_locked": true,
      "is_fictional": false,
      "index": 7,
      "show_id": 195753,
      "season_no": 1,
      "is_demo_premium": false,
      "is_free_unlocked": true,
      "media_size": 7719005,
      "published_on": "2023-04-19T07:38:55.106211+00:00",
      "thumbnail_image": "https://images.cdn.kukufm.com/w:200/f:jpg/q:85/https://s3.ap-south-1.amazonaws.com/kukufm/channel_icons/26c479db05654e44b6c84bde130aaa91.png",
      "web_uri": "/episode/governor-06",
      "view_type": "default",
      "unlocking_nudge_text": "",
      "unlocking_nudge_text_v2": "",
      "has_srt": false,
      "has_liked": false,
      "seek_position": 0,
      "can_download": true,
      "is_downloaded": false,
      "is_self": false,
      "unlock_type": "subscription",
      "transcript": {}
    },
    {
      "id": 636203,
      "title": "7. Padhavi thevaya ?",
      "slug": "governor-07",
      "status": "live",
      "image": "https://images.cdn.kukufm.com/f:webp/https://s3.ap-south-1.amazonaws.com/kukufm/channel_icons/26c479db05654e44b6c84bde130aaa91.png",
      "original_image": "https://s3.ap-south-1.amazonaws.com/kukufm/channel_icons/26c479db05654e44b6c84bde130aaa91.png",
      "duration_s": 557,
      "image_sizes": {
        "100": "https://images.cdn.kukufm.com/w:100/f:webp/q:85/https://s3.ap-south-1.amazonaws.com/kukufm/channel_icons/26c479db05654e44b6c84bde130aaa91.png",
        "150": "https://images.cdn.kukufm.com/w:150/f:webp/q:85/https://s3.ap-south-1.amazonaws.com/kukufm/channel_icons/26c479db05654e44b6c84bde130aaa91.png",
        "200": "https://images.cdn.kukufm.com/w:200/f:webp/q:85/https://s3.ap-south-1.amazonaws.com/kukufm/channel_icons/26c479db05654e44b6c84bde130aaa91.png",
        "300": "https://images.cdn.kukufm.com/w:300/f:webp/q:85/https://s3.ap-south-1.amazonaws.com/kukufm/channel_icons/26c479db05654e44b6c84bde130aaa91.png"
      },
      "n_likes": 0,
      "n_shares": 0,
      "n_plays": null,
      "n_listens": 486,
      "n_comments": 3,
      "cover_type": null,
      "content": {
        "converted_hls_url": "https://kukufm.akamaized.net/audio/7d0e8cab-8ef2-49fe-8d2a-e1ce7e3d46d8.m3u8",
        "audio_128kb": "https://kukufm.akamaized.net/audio/7d0e8cab-8ef2-49fe-8d2a-e1ce7e3d46d8128kb.m3u8",
        "audio_64kb": "https://kukufm.akamaized.net/audio/7d0e8cab-8ef2-49fe-8d2a-e1ce7e3d46d864kb.m3u8",
        "audio_24kb": "https://kukufm.akamaized.net/audio/7d0e8cab-8ef2-49fe-8d2a-e1ce7e3d46d824kb.m3u8"
      },
      "dynamic_link": "https://applinks.kukufm.com/VYMdYcBrc9meaNNn8",
      "is_premium": true,
      "is_play_locked": false,
      "is_locked": true,
      "is_fictional": false,
      "index": 8,
      "show_id": 195753,
      "season_no": 1,
      "is_demo_premium": false,
      "is_free_unlocked": true,
      "media_size": 11857474,
      "published_on": "2023-04-19T07:38:55.106211+00:00",
      "thumbnail_image": "https://images.cdn.kukufm.com/w:200/f:jpg/q:85/https://s3.ap-south-1.amazonaws.com/kukufm/channel_icons/26c479db05654e44b6c84bde130aaa91.png",
      "web_uri": "/episode/governor-07",
      "view_type": "default",
      "unlocking_nudge_text": "",
      "unlocking_nudge_text_v2": "",
      "has_srt": false,
      "has_liked": false,
      "seek_position": 0,
      "can_download": true,
      "is_downloaded": false,
      "is_self": false,
      "unlock_type": "subscription",
      "transcript": {}
    },
    {
      "id": 636205,
      "title": "8. Paarapatchangal",
      "slug": "governor-08",
      "status": "live",
      "image": "https://images.cdn.kukufm.com/f:webp/https://s3.ap-south-1.amazonaws.com/kukufm/channel_icons/26c479db05654e44b6c84bde130aaa91.png",
      "original_image": "https://s3.ap-south-1.amazonaws.com/kukufm/channel_icons/26c479db05654e44b6c84bde130aaa91.png",
      "duration_s": 424,
      "image_sizes": {
        "100": "https://images.cdn.kukufm.com/w:100/f:webp/q:85/https://s3.ap-south-1.amazonaws.com/kukufm/channel_icons/26c479db05654e44b6c84bde130aaa91.png",
        "150": "https://images.cdn.kukufm.com/w:150/f:webp/q:85/https://s3.ap-south-1.amazonaws.com/kukufm/channel_icons/26c479db05654e44b6c84bde130aaa91.png",
        "200": "https://images.cdn.kukufm.com/w:200/f:webp/q:85/https://s3.ap-south-1.amazonaws.com/kukufm/channel_icons/26c479db05654e44b6c84bde130aaa91.png",
        "300": "https://images.cdn.kukufm.com/w:300/f:webp/q:85/https://s3.ap-south-1.amazonaws.com/kukufm/channel_icons/26c479db05654e44b6c84bde130aaa91.png"
      },
      "n_likes": 0,
      "n_shares": 0,
      "n_plays": null,
      "n_listens": 427,
      "n_comments": 0,
      "cover_type": null,
      "content": {
        "converted_hls_url": "https://kukufm.akamaized.net/audio/df7856a3-99eb-4dc0-b601-dc7543a2a01f.m3u8",
        "audio_128kb": "https://kukufm.akamaized.net/audio/df7856a3-99eb-4dc0-b601-dc7543a2a01f128kb.m3u8",
        "audio_64kb": "https://kukufm.akamaized.net/audio/df7856a3-99eb-4dc0-b601-dc7543a2a01f64kb.m3u8",
        "audio_24kb": "https://kukufm.akamaized.net/audio/df7856a3-99eb-4dc0-b601-dc7543a2a01f24kb.m3u8"
      },
      "dynamic_link": "https://applinks.kukufm.com/cJSJ5ZPzXRYMo4ym9",
      "is_premium": true,
      "is_play_locked": false,
      "is_locked": true,
      "is_fictional": false,
      "index": 9,
      "show_id": 195753,
      "season_no": 1,
      "is_demo_premium": false,
      "is_free_unlocked": true,
      "media_size": 9504984,
      "published_on": "2023-04-19T07:38:55.106211+00:00",
      "thumbnail_image": "https://images.cdn.kukufm.com/w:200/f:jpg/q:85/https://s3.ap-south-1.amazonaws.com/kukufm/channel_icons/26c479db05654e44b6c84bde130aaa91.png",
      "web_uri": "/episode/governor-08",
      "view_type": "default",
      "unlocking_nudge_text": "",
      "unlocking_nudge_text_v2": "",
      "has_srt": false,
      "has_liked": false,
      "seek_position": 0,
      "can_download": true,
      "is_downloaded": false,
      "is_self": false,
      "unlock_type": "subscription",
      "transcript": {}
    },
    {
      "id": 636207,
      "title": "9. India'vin sirandha aalunargal - conclusion",
      "slug": "governor-09-end",
      "status": "live",
      "image": "https://images.cdn.kukufm.com/f:webp/https://s3.ap-south-1.amazonaws.com/kukufm/channel_icons/26c479db05654e44b6c84bde130aaa91.png",
      "original_image": "https://s3.ap-south-1.amazonaws.com/kukufm/channel_icons/26c479db05654e44b6c84bde130aaa91.png",
      "duration_s": 366,
      "image_sizes": {
        "100": "https://images.cdn.kukufm.com/w:100/f:webp/q:85/https://s3.ap-south-1.amazonaws.com/kukufm/channel_icons/26c479db05654e44b6c84bde130aaa91.png",
        "150": "https://images.cdn.kukufm.com/w:150/f:webp/q:85/https://s3.ap-south-1.amazonaws.com/kukufm/channel_icons/26c479db05654e44b6c84bde130aaa91.png",
        "200": "https://images.cdn.kukufm.com/w:200/f:webp/q:85/https://s3.ap-south-1.amazonaws.com/kukufm/channel_icons/26c479db05654e44b6c84bde130aaa91.png",
        "300": "https://images.cdn.kukufm.com/w:300/f:webp/q:85/https://s3.ap-south-1.amazonaws.com/kukufm/channel_icons/26c479db05654e44b6c84bde130aaa91.png"
      },
      "n_likes": 0,
      "n_shares": 0,
      "n_plays": null,
      "n_listens": 390,
      "n_comments": 0,
      "cover_type": null,
      "content": {
        "converted_hls_url": "https://kukufm.akamaized.net/audio/4f0cb79a-7834-4669-9507-ff028d9bfd26.m3u8",
        "audio_128kb": "https://kukufm.akamaized.net/audio/4f0cb79a-7834-4669-9507-ff028d9bfd26128kb.m3u8",
        "audio_64kb": "https://kukufm.akamaized.net/audio/4f0cb79a-7834-4669-9507-ff028d9bfd2664kb.m3u8",
        "audio_24kb": "https://kukufm.akamaized.net/audio/4f0cb79a-7834-4669-9507-ff028d9bfd2624kb.m3u8"
      },
      "dynamic_link": "https://applinks.kukufm.com/9Khea8p8jG6gDPw38",
      "is_premium": true,
      "is_play_locked": false,
      "is_locked": true,
      "is_fictional": false,
      "index": 10,
      "show_id": 195753,
      "season_no": 1,
      "is_demo_premium": false,
      "is_free_unlocked": true,
      "media_size": 8239056,
      "published_on": "2023-04-19T07:38:55.106211+00:00",
      "thumbnail_image": "https://images.cdn.kukufm.com/w:200/f:jpg/q:85/https://s3.ap-south-1.amazonaws.com/kukufm/channel_icons/26c479db05654e44b6c84bde130aaa91.png",
      "web_uri": "/episode/governor-09-end",
      "view_type": "default",
      "unlocking_nudge_text": "",
      "unlocking_nudge_text_v2": "",
      "has_srt": false,
      "has_liked": false,
      "seek_position": 0,
      "can_download": true,
      "is_downloaded": false,
      "is_self": false,
      "unlock_type": "subscription",
      "transcript": {}
    }
  ],
  "has_more": false,
  "n_episodes": 10,
  "n_pages": 1,
  "page": 1,
  "support_sticker": "",
  "is_skip_show_page": false,
  "season_n_episodes": 10,
  "last_unlocked_episode_index": 1,
  "first_locked_episode_title": "1. Uruvaana kadhai",
  "seo_description": "",
  "ads_info": {
    "interstitial_unit_id": "ca-app-pub-4561182393559685/8104245285",
    "reward_unit_id": "ca-app-pub-4561182393559685/3766806802"
  }
}